Workbook

Sheet KPI  Monthly Report
A1: Month | B1: Oct | D1: Nov | F1: Dec | H1: Jan | J1: Feb | L1: Mar | N1: Apr | P1: May | R1: Jun
A2: <KPI>
A3: セッション / 세션 | B3: 10000 | C3: --- | D3: 10000 | E3: --- | F3: 12000 | G3: --- | H3: 22000 | I3: --- | J3: 20000 | K3: --- | L3: 23000 | M3: --- | N3: 19000 | O3: --- | Q3: --- | S3: ---
A4: CVR | B4: 0.003 | C4: --- | D4: 0.003 | E4: --- | F4: 0.0035 | G4: --- | H4: 0.004 | I4: --- | J4: 0.0075 | K4: --- | L4: 0.0075 | M4: --- | N4: 0.0075 | O4: --- | Q4: --- | S4: ---
A5: 客単価 / 객단가 | B5: 30000 | C5: --- | D5: 30000 | E5: --- | F5: 42000 | G5: --- | H5: 30000 | I5: --- | J5: 35000 | K5: --- | L5: 32000 | M5: --- | N5: 32000 | O5: --- | Q5: --- | S5: ---
A6: 売上 / 매출 | B6: =B3*B4*B5 -> 900000 | C6: --- | D6: =D3*D4*D5 -> 900000 | E6: --- | F6: =F3*F4*F5 -> 1764000 | G6: --- | H6: =H3*H4*H5 -> 2640000 | I6: --- | J6: =J3*J4*J5 -> 5250000 | K6: --- | L6: =L3*L4*L5 -> 5520000 | M6: --- | N6: =N3*N4*N5 -> 4560000 | O6: --- | Q6: --- | S6: ---
A7: 広告費 / 광고비 | B7: 120000 | C7: --- | D7: 120000 | E7: --- | F7: 120000 | G7: --- | H7: 120000 | I7: --- | J7: 120000 | K7: --- | L7: 120000 | M7: --- | N7: 120000 | O7: --- | Q7: --- | S7: ---
A8: IG FOLLOWER | B8: 2000 | C8: --- | D8: 3200 | E8: --- | F8: 3700 | G8: --- | H8: 5600 | I8: --- | J8: 6000 | K8: --- | L8: 7000 | M8: --- | N8: 7000 | O8: --- | Q8: --- | S8: ---
A10: <EC PERFORMANCE> | C10: achievement rate | E10: achievement rate | G10: achievement rate | I10: achievement rate | K10: achievement rate | M10: achievement rate | O10: achievement rate | Q10: achievement rate | S10: achievement rate
A11: セッション / 세션 | B11: =INDEX('Shopify KPI Monthly'!$A2:$Z2, (COLUMN()/2)+1) -> 7749 | C11: =B11/B3 -> 0.7749 | D11: =INDEX('Shopify KPI Monthly'!$A2:$Z2, (COLUMN()/2)+1) -> 9533 | E11: =D11/D3 -> 0.9533 | F11: =INDEX('Shopify KPI Monthly'!$A2:$Z2, (COLUMN()/2)+1) -> 9714 | G11: =F11/F3 -> 0.8095 | H11: =INDEX('Shopify KPI Monthly'!$A2:$Z2, (COLUMN()/2)+1) -> 20596 | I11: =H11/H3 -> 0.93618182 | J11: =INDEX('Shopify KPI Monthly'!$A2:$Z2, (COLUMN()/2)+1) -> 8375 | K11: =J11/J3 -> 0.41875 | L11: =INDEX('Shopify KPI Monthly'!$A2:$Z2, (COLUMN()/2)+1) -> 0 | M11: =L11/L3 -> 0 | N11: =INDEX('Shopify KPI Monthly'!$A2:$Z2, (COLUMN()/2)+1) -> 0 | O11: =N11/N3 -> 0 | P11: =INDEX('Shopify KPI Monthly'!$A2:$Z2, (COLUMN()/2)+1) -> 0 | Q11: =P11/P3 -> #DIV/0! | R11: =INDEX('Shopify KPI Monthly'!$A2:$Z2, (COLUMN()/2)+1) -> 0 | S11: =R11/R3 -> #DIV/0!
A12: CVR | B12: =INDEX('Shopify KPI Monthly'!$A3:$Z3, (COLUMN()/2)+1) / 100 -> 0.0036133695 | C12: =B12/B4 -> 1.2044565 | D12: =INDEX('Shopify KPI Monthly'!$A3:$Z3, (COLUMN()/2)+1) / 100 -> 0.0037763558 | E12: =D12/D4 -> 1.2587853 | F12: =INDEX('Shopify KPI Monthly'!$A3:$Z3, (COLUMN()/2)+1) / 100 -> 0.0051472102 | G12: =F12/F4 -> 1.4706315 | H12: =INDEX('Shopify KPI Monthly'!$A3:$Z3, (COLUMN()/2)+1) / 100 -> 0.0094678578 | I12: =H12/H4 -> 2.3669645 | J12: =INDEX('Shopify KPI Monthly'!$A3:$Z3, (COLUMN()/2)+1) / 100 -> 0.012298507 | K12: =J12/J4 -> 1.639801 | L12: =INDEX('Shopify KPI Monthly'!$A3:$Z3, (COLUMN()/2)+1) / 100 -> 0 | M12: =L12/L4 -> 0 | N12: =INDEX('Shopify KPI Monthly'!$A3:$Z3, (COLUMN()/2)+1) / 100 -> 0 | O12: =N12/N4 -> 0 | P12: =INDEX('Shopify KPI Monthly'!$A3:$Z3, (COLUMN()/2)+1) / 100 -> 0 | Q12: =P12/P4 -> #DIV/0! | R12: =INDEX('Shopify KPI Monthly'!$A3:$Z3, (COLUMN()/2)+1) / 100 -> 0 | S12: =R12/R4 -> #DIV/0!
A13: 客単価 / 객단가 | B13: =INDEX('Shopify KPI Monthly'!$A4:$Z4, (COLUMN()/2)+1) -> 26710.714 | C13: =B13/B5 -> 0.89035713 | D13: =INDEX('Shopify KPI Monthly'!$A4:$Z4, (COLUMN()/2)+1) -> 41486.888 | E13: =D13/D5 -> 1.3828963 | F13: =INDEX('Shopify KPI Monthly'!$A4:$Z4, (COLUMN()/2)+1) -> 35364 | G13: =F13/F5 -> 0.842 | H13: =INDEX('Shopify KPI Monthly'!$A4:$Z4, (COLUMN()/2)+1) -> 34978.52 | I13: =H13/H5 -> 1.1659507 | J13: =INDEX('Shopify KPI Monthly'!$A4:$Z4, (COLUMN()/2)+1) -> 31001.846 | K13: =J13/J5 -> 0.88576703 | L13: =INDEX('Shopify KPI Monthly'!$A4:$Z4, (COLUMN()/2)+1) -> 0 | M13: =L13/L5 -> 0 | N13: =INDEX('Shopify KPI Monthly'!$A4:$Z4, (COLUMN()/2)+1) -> 0 | O13: =N13/N5 -> 0 | P13: =INDEX('Shopify KPI Monthly'!$A4:$Z4, (COLUMN()/2)+1) -> 0 | Q13: =P13/P5 -> #DIV/0! | R13: =INDEX('Shopify KPI Monthly'!$A4:$Z4, (COLUMN()/2)+1) -> 0 | S13: =R13/R5 -> #DIV/0!
A14: 売上 / 매출 | B14: =INDEX('Shopify KPI Monthly'!$A5:$Z5, (COLUMN()/2)+1) -> 747900 | C14: =B14/B6 -> 0.831 | D14: =INDEX('Shopify KPI Monthly'!$A5:$Z5, (COLUMN()/2)+1) -> 1493528 | E14: =D14/D6 -> 1.6594756 | F14: =INDEX('Shopify KPI Monthly'!$A5:$Z5, (COLUMN()/2)+1) -> 1686600 | G14: =F14/F6 -> 0.95612245 | H14: =INDEX('Shopify KPI Monthly'!$A5:$Z5, (COLUMN()/2)+1) -> 6556292 | I14: =H14/H6 -> 2.4834439 | J14: =INDEX('Shopify KPI Monthly'!$A5:$Z5, (COLUMN()/2)+1) -> 2791294 | K14: =J14/J6 -> 0.53167505 | L14: =INDEX('Shopify KPI Monthly'!$A5:$Z5, (COLUMN()/2)+1) -> 0 | M14: =L14/L6 -> 0 | N14: =INDEX('Shopify KPI Monthly'!$A5:$Z5, (COLUMN()/2)+1) -> 0 | O14: =N14/N6 -> 0 | P14: =INDEX('Shopify KPI Monthly'!$A5:$Z5, (COLUMN()/2)+1) -> 0 | Q14: =P14/P6 -> #DIV/0! | R14: =INDEX('Shopify KPI Monthly'!$A5:$Z5, (COLUMN()/2)+1) -> 0 | S14: =R14/R6 -> #DIV/0!
A15: 注文数 / 주문수 | B15: =INDEX('Shopify KPI Monthly'!$A6:$Z6, (COLUMN()/2)+1) -> 28 | C15: --- | D15: =INDEX('Shopify KPI Monthly'!$A6:$Z6, (COLUMN()/2)+1) -> 36 | E15: --- | F15: =INDEX('Shopify KPI Monthly'!$A6:$Z6, (COLUMN()/2)+1) -> 50 | G15: --- | H15: =INDEX('Shopify KPI Monthly'!$A6:$Z6, (COLUMN()/2)+1) -> 196 | I15: --- | J15: =INDEX('Shopify KPI Monthly'!$A6:$Z6, (COLUMN()/2)+1) -> 104 | K15: --- | L15: =INDEX('Shopify KPI Monthly'!$A6:$Z6, (COLUMN()/2)+1) -> 0 | M15: --- | N15: =INDEX('Shopify KPI Monthly'!$A6:$Z6, (COLUMN()/2)+1) -> 0 | O15: --- | P15: =INDEX('Shopify KPI Monthly'!$A6:$Z6, (COLUMN()/2)+1) -> 0 | Q15: --- | R15: =INDEX('Shopify KPI Monthly'!$A6:$Z6, (COLUMN()/2)+1) -> 0 | S15: ---
A16: リピーター | B16: =INDEX('Shopify KPI Monthly'!$A7:$Z7, (COLUMN()/2)+1) / 100 -> 0.076923077 | D16: =INDEX('Shopify KPI Monthly'!$A7:$Z7, (COLUMN()/2)+1) / 100 -> 0.15625 | E16: --- | F16: =INDEX('Shopify KPI Monthly'!$A7:$Z7, (COLUMN()/2)+1) / 100 -> 0.10638298 | G16: --- | H16: =INDEX('Shopify KPI Monthly'!$A7:$Z7, (COLUMN()/2)+1) / 100 -> 0.13407821 | I16: --- | J16: =INDEX('Shopify KPI Monthly'!$A7:$Z7, (COLUMN()/2)+1) / 100 -> 0.23404255 | K16: --- | L16: =INDEX('Shopify KPI Monthly'!$A7:$Z7, (COLUMN()/2)+1) / 100 -> 0 | M16: --- | N16: =INDEX('Shopify KPI Monthly'!$A7:$Z7, (COLUMN()/2)+1) / 100 -> 0 | O16: --- | P16: =INDEX('Shopify KPI Monthly'!$A7:$Z7, (COLUMN()/2)+1) / 100 -> 0 | Q16: --- | R16: =INDEX('Shopify KPI Monthly'!$A7:$Z7, (COLUMN()/2)+1) / 100 -> 0 | S16: ---
A17: 広告費 / 광고비 | B17: 120000 | C17: --- | D17: 120000 | E17: --- | F17: 120000 | G17: --- | H17: 320000 | I17: --- | J17: 141550 | K17: --- | L17: 120000 | M17: --- | N17: 120000 | O17: --- | P17: 120000 | Q17: --- | R17: 120000 | S17: ---
A18: IG FOLLOWER | B18: 2105 | C18: =B18/B8 -> 1.0525 | D18: 3084 | E18: =D18/D8 -> 0.96375 | F18: 3794 | G18: =F18/F8 -> 1.0254054 | H18: 5757 | I18: =H18/H8 -> 1.0280357 | J18: 5973 | K18: =J18/J8 -> 0.9955 | M18: =L18/L8 -> 0 | O18: =N18/N8 -> 0 | Q18: =P18/P8 -> #DIV/0! | S18: =R18/R8 -> #DIV/0!
A19: Memo | C19: --- | E19: --- | G19: --- | I19: --- | K19: --- | M19: --- | O19: --- | Q19: --- | S19: ---
A20: Memo | C20: --- | E20: --- | G20: --- | I20: --- | K20: --- | M20: --- | O20: --- | Q20: --- | S20: ---
A22: <IG PERFORMANCE>
C23: Engagement率 | E23: Engagement率
A24: Prfile Access | B24: 12649 | C24: --- | D24: 14276 | E24: --- | F24: --- | H24: --- | J24: 7754
A25: Web Click | B25: 2717 | C25: --- | D25: 2875 | E25: --- | F25: --- | H25: --- | J25: 2408
A26: Account Reach | B26: 215517 | C26: --- | D26: 98274 | E26: --- | F26: --- | H26: --- | J26: 71432
A27: Account View | B27: 667824 | C27: --- | D27: 690490 | E27: --- | F27: --- | H27: --- | J27: 292562
A28: Feed | B28: 17 | C28: --- | D28: 6 | E28: 5.02 %/9018 | F28: --- | H28: --- | J28: 13 | K28: 150(good)/89(save)
A29: Reel | B29: 1 | C29: --- | D29: 2 | E29: 2.48 %/4191 | F29: --- | H29: --- | J29: 0 | K29: 78(good)/10(save)
A30: Stories | B30: 153 | C30: --- | D30: 402 | E30: 92374 | F30: --- | H30: --- | J30: 250 | K30: 9,159(視聴完了)
A31: follower growth | F31: --- | H31: --- | J31: 216
A32: Memo | C32: --- | E32: --- | G32: --- | I32: --- | K32: --- | M32: --- | O32: --- | Q32: --- | S32: ---

Sheet Shopify KPI Monthly
A1: month | B1: 2025-10-01 | C1: 2025-11-01 | D1: 2025-12-01 | E1: 2026-01-01 | F1: 2026-02-01
A2: sessions | B2: 7749 | C2: 9533 | D2: 9714 | E2: 20596 | F2: 8375
A3: conversion_rate | B3: 0.36133695 | C3: 0.37763558 | D3: 0.51472102 | E3: 0.94678578 | F3: 1.2298507
A4: average_order_value | B4: 26710.714 | C4: 41486.888 | D4: 35364 | E4: 34978.52 | F4: 31001.846
A5: net_sales | B5: 747900 | C5: 1493528 | D5: 1686600 | E5: 6556292 | F5: 2791294
A6: orders | B6: 28 | C6: 36 | D6: 50 | E6: 196 | F6: 104
A7: returning_customer_rate | B7: 7.6923077 | C7: 15.625 | D7: 10.638298 | E7: 13.407821 | F7: 23.404255

Sheet Year-round promotion
B1: Month | C1: 施作 | E1: 内容 | G1: 期間 | H1: EC | I1: AD | J1: SNS | K1: 強化アイテム
A2: SALES PROMOTION | B2: JAN | C2: POP UP THANK YOU SALE | D2: 신년 세일 | E2: 対象商品20％オフ。イベントで集めたフォロワーをCVに繋げる施策 | F2: 대상 상품 20% 할인. 이벤트로 모은 팔로워를 CV로 연결하는 시책 | G2: 1/16-18 | K2: --- | L2: --- | M2: ---
C3: SALE | D3: 신년 세일 | E3: アウター30%オフ | F3: =IFERROR(__xludf.DUMMYFUNCTION("GOOGLETRANSLATE(E3,""ja"",""ko"")"),"아우터 30% 할인") -> 아우터 30% 할인 | G3: 1/23-2/1 | I3: セールの広告を10パターンほど量産。左の内容を匂わせるようなものも含めつつ、検証可能なバリエーションを用意して。 | J3: ①お買い得感を煽るものはストーリーズでメッセージを添えて接客。 ②フィードでもセールの告知はするが、ブランディングを担保する方を優先する方向で。 | K3: --- | L3: --- | M3: ---
C4: POINT SYSTEM | E4: 購入金額に応じたポイント制を導入.還元率は2％。1万円以上購入の際に限る | F4: =IFERROR(__xludf.DUMMYFUNCTION("GOOGLETRANSLATE(E4,""ja"",""ko"")"),"구입 금액에 따른 포인트제를 도입.환원율은 2%. 1만엔 이상 구입 시에 한함") -> 구입 금액에 따른 포인트제를 도입.환원율은 2%. 1만엔 이상 구입 시에 한함 | G4: 45676
B5: Feb | C5: ファイナルセール | E5: 全品２０％オフ | F5: =IFERROR(__xludf.DUMMYFUNCTION("GOOGLETRANSLATE(E5,""ja"",""ko"")"),"전품 20% 할인") -> 전품 20% 할인
C6: CLEARANCE SALE | D6: 발렌타인 기획전 (선물) | E6: ただお買い得なだけじゃなく、戦略的に販売をしていく必要あり。 ・単価の高いコート類はまだまだこれからも活躍することを訴求 ・ニット類との合わせがい、コーデがい、などを促進 ・シーズンを跨いだとしても使えるタイムレスなピースを訴求 etc,,, | F6: 단순히 가격이 저렴하다는 점뿐만 아니라, 전략적인 판매 접근이 필요함. ・단가가 높은 코트류는 남은 시즌 동안에도 충분히 활용 가능하다는 점을 소구 ・니트류와 매치하는 재미, 코디 활용도가 높다는 점 등을 강조 ・시즌을 넘겨도 입을 수 있는 타임리스(유행을 타지 않는) 아이템임을 소구 등등... | I6: セールの広告を10パターンほど量産。左の内容を匂わせるようなものも含めつつ、検証可能なバリエーションを用意して。 | J6: ①お買い得感を煽るものはストーリーズでメッセージを添えて接客。 ②フィードでもセールの告知はするが、ブランディングを担保する方を優先する方向で。 | K6: --- | L6: --- | M6: ---
C7: PRE-ORDER EVENT | E7: 25SSの新作先行予約会。予約特典として「15％オフ」「次回使えるポイント」を付与。「今すぐ着られないもの」を1月に買ってもらうための、ポイントアップや限定ノベルティの強力なフックが必要。 | F7: =IFERROR(__xludf.DUMMYFUNCTION("GOOGLETRANSLATE(E7,""ja"",""ko"")"),"25SS의 신작 선행 예약회. 예약 특전으로서 「15%오프」 「다음 번 사용할 수 있는 포인트」를 부여. 「지금 입을 수 없는 것」을 1월에 사 받기 위한, 포인트 업이나 한정 노벨티의 강력한 훅이 필요.") -> 25SS의 신작 선행 예약회. 예약 특전으로서 「15%오프」 「다음 번 사용할 수 있는 포인트」를 부여. 「지금 입을 수 없는 것」을 1월에 사 받기 위한, 포인트 업이나 한정 노벨티의 강력한 훅이 필요. | G7: SSリリース開始日確認中 | J7: スタッフによる**「徹底的なライブ配信（インスタライブ）」**で、素材感や160cm/150cm台それぞれの着用感を伝え、発売前に「完売必至」の空気を作ります。
B8: Mar | C8: LINE COUPON | E8: LINEの開封率が良いので、割引クーポンを配信してテスト。 | F8: =IFERROR(__xludf.DUMMYFUNCTION("GOOGLETRANSLATE(E8,""ja"",""ko"")"),"LINE의 개봉율이 좋기 때문에, 할인 쿠폰을 전달해 테스트.") -> LINE의 개봉율이 좋기 때문에, 할인 쿠폰을 전달해 테스트.
C9: NEW RELEASAE IN SPRING | D9: 새생활 응원 기획전 (입학·신사회인 대상 상품 제안) | E9: プレオーダーでオフをやっているので、ここでは「限定ノベルティ」を付与 | F9: =IFERROR(__xludf.DUMMYFUNCTION("GOOGLETRANSLATE(E9,""ja"",""ko"")"),"프리 오더로 오프를하고 있기 때문에, 여기에서는 「한정 참신」을 부여") -> 프리 오더로 오프를하고 있기 때문에, 여기에서는 「한정 참신」을 부여 | G9: 3/5-10 | K9: ? | L9: ? | M9: ?
C10: "Perfect Tailoring" Campaign | E10: 卒業式や入学式、そのほか新年度の行事に使えるジャケット系、セットアップ系のアイテムを訴求。 | F10: =IFERROR(__xludf.DUMMYFUNCTION("GOOGLETRANSLATE(E10,""ja"",""ko"")"),"졸업식이나 입학식, 그 외 신년도의 행사에 사용할 수 있는 재킷계, 셋업계의 아이템을 소구.") -> 졸업식이나 입학식, 그 외 신년도의 행사에 사용할 수 있는 재킷계, 셋업계의 아이템을 소구. | G10: 3/1- | H10: サイズ感や着心地のレビューを強化。特に「日本人女性の体型にどうフィットするか」のスタッフスナップを掲載。 | J10: サイズ感や着心地のレビューを強化。特に「日本人女性の体型にどうフィットするか」のスタッフスナップを掲載。
B11: Apr
B15: May
B19: Jun | D19: 장마철에 딱! 나일론 백 제안
D20: 여름 신상 론칭
B22: Jul | D22: 여름 본격 시작! 스타일의 포인트, 백으로 완성하세요.
D23: 플라잉 썸머 세일
B24: Aug | D24: 썸머 세일
D25: 가을 시작
B27: Sep | D27: 가을 아이템 제안
D28: 컬러별 백 제안
B30: Oct | D30: 할로윈
B32: Nov | D32: 블랙프라이데이
D33: 크리스마스 기획전
B34: Dec | D34: 크리스마스 기획전
D35: 연말 세일

Sheet Year-round promotion（old）
A1: SALES PROMOTION ＊右の施策に、2Buyやノベルティ、SALE、LINEクーポンなどをうまく絡ませながら実施。 | B1: JAN | C1: 新年セール | D1: 신년 세일
C2: お年玉ノベルティ企画 | D2: 세뱃돈 노벨티 이벤트
C3: Re Start（年始心機一転提案企画） | D3: Re Start (신년 마음가짐 제안 기획)
C4: 福袋企画
B5: Feb | C5: バレンタイン関連企画（ギフト） | D5: 발렌타인 기획전 (선물)
C6: 春の新作訴求 | D6: 봄 신제품 프로모션
C7: ホワイトデー（ギフト） | D7: 화이트데이 선물
C8: 卒業、入学、
B9: Mar | C9: 春の新作 本格ローンチ | D9: 봄 신상 정식 론칭
C10: 新生活応援企画 | D10: 새생활 응원 기획전
C11: 卒業、入学、
B13: Apr | C13: 新生活応援企画（継続） | D13: 새생활 응원 기획전 (연속 진행)
C14: GWの準備企画 | D14: 골든위크 준비 기획전
B17: May | C17: 梅雨時から夏に使えるアイテム訴求 | D17: 장마철부터 여름까지 활용할 수 있는 아이템 홍보
C18: 春アイテムの一部セール | D18: 봄 아이템 일부 세일
B21: Jun | C21: 梅雨のタイミングで使えるアイテム訴求 | D21: 장마철부터 여름까지 활용할 수 있는 아이템 홍보
C22: 夏の新作ローンチ | D22: 여름 신상 론칭
B24: Jul | C24: 夏本番訴（薄着になる夏の主役級バッグ、など） | D24: 여름 본격 시작! 스타일의 포인트, 백으로 완성하세요.
C25: フライングサマーセール | D25: 플라잉 썸머 세일
B26: Aug | C26: サマーセール | D26: 썸머 세일
C27: 秋の立ち上がり | D27: 가을 시작
B29: Sep | C29: 秋アイテム訴求 | D29: 가을 아이템 제안
B32: Oct | C32: ハロウィーン | D32: 할로윈
B34: Nov | C34: ブラックフライデー | D34: 블랙프라이데이
C35: クリスマス訴求 | D35: 크리스마스 기획전
B36: Dec | C36: クリスマス訴求 | D36: 크리스마스 기획전
C37: 年末セール | D37: 연말 세일

Sheet PROMOTION LIST
A1: ISSUE | B1: KPI | C1: TASK | E1: ACTION
A2: 売り上げを上げたい 매출을 올리고 싶어요. | B2: 集客 / 세션 | C2: 露出、表示を増やす / 노출 확대 | D2: 広告などの手段で自社商品の露出や表示がされる場所を増やします。また、それらが表示される頻度を増やします。 광고 등의 수단을 통해 자사 상품이 노출되거나 표시되는 채널을 늘립니다. 또한, 그러한 노출의 빈도도 증가시킵니다. | E2: ・WEB広告運用 ・媒体広告出稿等 ・웹 광고 운영 ・매체 광고 집행 등
C3: クリックしたくする / 클릭 유도 | D3: 露出しているクリエイティブのクリック率を上げる＝クリック率を上げるには、訴求を明確にし、以下の4つの要素を意識したクリエイティブを心がける。 ・有益性：見る人に「自分にとって価値がある」と思わせる内容 ・緊急性：今すぐ行動したくなる訴求 ・超具体性：数字などを用いて伝わる具体的な表現 ・独自性：他と差別化できる独自の視点やデザイン “노출되고있는 크리에이티브의 클릭률을 높인다” = 클릭률을 높이기 위해서는 소구를 명확히 하고, 아래 4가지 요소를 의식한 크리에이티브를 제작하는 것이 중요 유익성: 보는 사람이 “나에게 가치가 있다”고 느끼게 하는 내용 긴급성: 지금 당장 행동하고 싶게 만드는 어필 초구체성: 숫자 등을 활용해 명확하게 전달되는 구체적인 표현 독자성: 타사와 차별화할 수 있는 독자적인 관점이나 디자인 | E3: ・クリエイティブの精度を上げる ・コピー付きのクリエイティブで顧客のニーズを掴む ・크리에이티브의 완성도를 높인다 ・카피(문구)가 포함된 크리에이티브로 고객의 니즈를 파악한다
C4: 他者に露出してもらう / 제 3자(타매체, 타인)를 통해 노출 | D4: メディアに取り上げられる、ブロガーに紹介していただく など、第三者の発信によって信頼性を高める工夫も効果的です。 미디어에 소개되거나 블로거가 제품을 소개해주는 등, 제3자를 통해 신뢰도를 높이는 전략도 효과적 | E4: PRリリース施策例 メディア掲載営業 ブログ掲載営業 など 프레스 보도자료 실행 예시 미디어 게재 세일즈 블로그 게재 세일즈 등
C5: 人に広めてもらう / 사람들에게 퍼트리게 하기 | D5: ファンやフォロワーを抱えている個人に紹介してもらうことで、集客を増やします。 팬이나 팔로워를 보유한 개인이 제품을 소개하도록 함으로써, 고객 유입(세션)을 늘림 | E5: SNS投稿促進施策 ギフティング（商品提供による投稿依頼） インフルエンサーアフィリエイト（成果報酬型の紹介施策） など SNS 게시 촉진 전략 기프팅(상품 제공을 통한 게시 요청) 인플루언서 어필리에이트(성과 기반의 소개형 프로모션) 등
C6: リード／リストを囲う 리드고객(잠재고객), 리스트를 확보 | D6: 潜在顧客をしっかりと見極めて、購買意欲の高いカスタマーを囲う。 잠재고객을 정확히 파악하여, 구매 의욕이 높은 고객을 확보 | E6: LINEの活用。メルマガの配信。 라인을 활용, 메일 매거진 발송
C7: 一度離脱した人に再アプローチする / 이탈 고객에게 재접근 (리타겟팅) | D7: 一度サイトを訪問したが離脱したユーザーに対し、リターゲティング広告やメール施策で再来訪を促進。 한번 사이트를 방문했지만 이탈한 사용자에게 리타게팅 광고나 이메일 마케팅을 통해 재방문 유도 | E7: リターゲティング広告施策 情報登録済み未購入者への販売促進施策 離脱ユーザーへの再訴求広告 など 리타게팅 광고 전략 정보 등록은 했지만 미구매 고객을 대상으로 한 판매 촉진 전략 이탈한 사용자에게 다시 어필하는 재타게팅 광고 등
B8: CVR / 전환률 | C8: 顧客のニーズ度合いを高める / 고객의 니즈 정도를 높이기 | D8: LPやECサイト内で、見込み顧客の「商品を欲しい」という気持ちを高めるコミュニケーションを行います。 「よくある悩み」「うまくいっていない状態」などの共感・課題提示を通して、購買意欲を刺激。「今だけの特典」などの限定訴求によって、「今買いたい」と思える状態をさらに強化 LP(랜딩페이지)나 EC사이트 내에서, 잠재고객의 “이 상품을 갖고 싶다”는 마음을 자극하는 커뮤니케이션을 진행합니다. “자주 겪는 고민”, “잘되지 않는 상황” 등의 공감과 문제 제시를 통해 구매 의욕을 자극하고, “지금만의 혜택”과 같은 한정 어필을 통해 ‘지금 사고 싶다’는 감정을 더욱 강화합니다. | E8: 期間限定クーポン 購入特典 など 기간 한정 쿠폰 구매 특전(사은품) 등
C9: 商品理解を高める /상품 이해도 높이기 | D9: 動画・写真・テキストを最大限に活用し、商品の魅力を簡潔かつ鮮明に理解いただける構成にします。 영상·사진·텍스트를 최대한 활용하여, 상품의 매력을 간결하고 명확하게 이해할 수 있는 구성으로 만듭니다. | E9: IGでの動画の投稿頻度を上げる。 ECサイト内の商品説明をもっと深掘りする 인스타그램에서 영상 게시 빈도를 높인다. EC사이트 내의 상품 설명을 더욱 깊이 있게 다룬다.

Sheet 2025.1
B1: 45658 | C1: 45659 | D1: 45660 | E1: 45661 | F1: 45662 | G1: 45663 | H1: 45664 | I1: 45665 | J1: 週締め | K1: 前週比 | M1: 45666 | N1: 45667 | O1: 45668 | P1: 45669 | Q1: 45670 | R1: 45671 | S1: 45672 | T1: 週締め | U1: 前週比 | W1: 45673 | X1: 45674 | Y1: 45675 | Z1: 45676 | AA1: 45677 | AB1: 45678 | AC1: 45679 | AD1: 週締め | AE1: 前週比 | AG1: 45680 | AH1: 45681 | AI1: 45682 | AJ1: 45683 | AK1: 45684 | AL1: 45685 | AM1: 45686 | AN1: 週締め | AO1: 前週比 | AQ1: 45687 | AR1: 45688 | AT1: 月締め | AU1: 先月比 | AV1: 当月KPI
B2: 水 | C2: 木 | D2: 金 | E2: 土 | F2: 日 | G2: 月 | H2: 火 | I2: 水 | M2: 木 | N2: 金 | O2: 土 | P2: 日 | Q2: 月 | R2: 火 | S2: 水 | W2: 木 | X2: 金 | Y2: 土 | Z2: 日 | AA2: 月 | AB2: 火 | AC2: 水 | AG2: 木 | AH2: 金 | AI2: 土 | AJ2: 日 | AK2: 月 | AL2: 火 | AM2: 水 | AQ2: 木 | AR2: 金
A3: 売り上げ | B3: 37070 | C3: 15620 | D3: 36296 | E3: 55509 | F3: 24497 | G3: 26615 | H3: 0 | I3: 86175 | J3: =SUM(C3:I3) -> 244712 | M3: 6710 | N3: 0 | O3: 58718 | P3: 37730 | Q3: 7480 | R3: 0 | S3: 17710 | T3: =SUM(M3:S3) -> 128348 | U3: =T3/J3 -> 0.52448593 | W3: 0 | X3: 6000 | Y3: 17900 | Z3: 16800 | AA3: 8800 | AB3: 3800 | AC3: 0 | AD3: =SUM(W3:AC3) -> 53300 | AE3: =AD3/T3 -> 0.41527722 | AG3: 0 | AH3: 15400 | AI3: 4800 | AJ3: 0 | AK3: 30800 | AL3: 0 | AM3: 32600 | AN3: =SUM(AG3:AM3) -> 83600 | AO3: =AN3/AD3 -> 1.5684803 | AQ3: 19200 | AR3: 5100 | AT3: 617480 | AU3: 1.54
A4: 注文数（人数） | B4: 2 | C4: 1 | D4: 3 | E4: 5 | F4: 2 | G4: 2 | H4: 0 | I4: 3 | J4: =SUM(C4:I4) -> 16 | M4: 1 | N4: 0 | O4: 3 | P4: 2 | Q4: 1 | R4: 0 | S4: 1 | T4: =SUM(M4:S4) -> 8 | U4: =T4/J4 -> 0.5 | W4: 0 | X4: 1 | Y4: 1 | Z4: 2 | AA4: 1 | AB4: 1 | AC4: 0 | AD4: =SUM(W4:AC4) -> 6 | AE4: =AD4/T4 -> 0.75 | AG4: 0 | AH4: 1 | AI4: 2 | AJ4: 0 | AK4: 1 | AL4: 0 | AM4: 3 | AN4: =SUM(AG4:AM4) -> 7 | AO4: =AN4/AD4 -> 1.1666667 | AQ4: 2 | AR4: 1 | AT4: 44 | AU4: 1.76
A5: 客単価 | B5: =B3/B4 -> 18535 | C5: =C3/C4 -> 15620 | D5: =D3/D4 -> 12098.667 | E5: =E3/E4 -> 11101.8 | F5: =F3/F4 -> 12248.5 | G5: =G3/G4 -> 13307.5 | H5: 0 | I5: 0 | J5: =AVERAGE(C5:I5) -> 9196.6381 | M5: 31348 | N5: 29431 | O5: 32262 | P5: =P3/P4 -> 18865 | Q5: =Q3/Q4 -> 7480 | R5: 0 | S5: 0 | T5: =AVERAGE(M5:S5) -> 17055.143 | U5: =T5/J5 -> 1.8544976 | W5: 0 | X5: =X3/X4 -> 6000 | Y5: =Y3/Y4 -> 17900 | Z5: =Z3/Z4 -> 8400 | AA5: =AA3/AA4 -> 8800 | AB5: =AB3/AB4 -> 3800 | AC5: 0 | AD5: =AVERAGE(W5:AC5) -> 6414.2857 | AE5: =AD5/T5 -> 0.376091 | AG5: 0 | AH5: =AH3/AH4 -> 15400 | AI5: =AI3/AI4 -> 2400 | AJ5: 0 | AK5: =AK3/AK4 -> 30800 | AL5: 0 | AM5: =AM3/AM4 -> 10866.667 | AN5: =AVERAGE(AG5:AM5) -> 8495.2381 | AO5: =AN5/AD5 -> 1.3244246 | AQ5: =AQ3/AQ4 -> 9600 | AR5: =AR3/AR4 -> 5100 | AT5: 12137 | AU5: 0.88
A6: セッション | B6: 1098 | C6: 1066 | D6: 832 | E6: 1439 | F6: 1758 | G6: 1332 | H6: 1295 | I6: 1266 | J6: =SUM(C6:I6) -> 8988 | M6: 997 | N6: 1094 | O6: 1433 | P6: 1422 | Q6: 1293 | R6: 1004 | S6: 479 | T6: =SUM(M6:S6) -> 7722 | U6: =T6/J6 -> 0.85914553 | W6: 1205 | X6: 1029 | Y6: 1107 | Z6: 1244 | AA6: 1073 | AB6: 1017 | AC6: 955 | AD6: =SUM(W6:AC6) -> 7630 | AE6: =AD6/T6 -> 0.98808599 | AG6: 988 | AH6: 899 | AI6: 1062 | AJ6: 1237 | AK6: 991 | AL6: 960 | AM6: 985 | AN6: =SUM(AG6:AM6) -> 7122 | AO6: =AN6/AD6 -> 0.93342071 | AQ6: 981 | AR6: 935 | AT6: 35639 | AU6: 1.44
A7: CVR | B7: =B4/B6 -> 0.0018214936 | C7: =C4/C6 -> 0.0009380863 | D7: =D4/D6 -> 0.0036057692 | E7: =E4/E6 -> 0.0034746352 | F7: =F4/F6 -> 0.0011376564 | G7: =G4/G6 -> 0.0015015015 | H7: =H4/H6 -> 0 | I7: =I4/I6 -> 0.0023696682 | J7: =J4/J6 -> 0.0017801513 | M7: =M4/M6 -> 0.001003009 | N7: =N4/N6 -> 0 | O7: =O4/O6 -> 0.0020935101 | P7: =P4/P6 -> 0.0014064698 | Q7: =Q4/Q6 -> 0.0007733952 | R7: =R4/R6 -> 0 | S7: =S4/S6 -> 0.0020876827 | T7: =T4/T6 -> 0.001036001 | U7: =T7/J7 -> 0.58197358 | W7: =W4/W6 -> 0 | X7: =X4/X6 -> 0.0009718173 | Y7: =Y4/Y6 -> 0.00090334237 | Z7: =Z4/Z6 -> 0.001607717 | AA7: =AA4/AA6 -> 0.00093196645 | AB7: =AB4/AB6 -> 0.00098328417 | AC7: =AC4/AC6 -> 0 | AD7: =AVERAGE(W7:AC7) -> 0.00077116105 | AE7: =AD7/T7 -> 0.7443632 | AG7: =AG4/AG6 -> 0 | AH7: =AH4/AH6 -> 0.0011123471 | AI7: =AI4/AI6 -> 0.0018832392 | AJ7: =AJ4/AJ6 -> 0 | AK7: =AK4/AK6 -> 0.0010090817 | AL7: =AL4/AL6 -> 0 | AM7: =AM4/AM6 -> 0.0030456853 | AN7: =AVERAGE(AG7:AM7) -> 0.0010071933 | AO7: =AN7/AD7 -> 1.3060739 | AQ7: =AQ4/AQ6 -> 0.002038736 | AR7: =AR4/AR6 -> 0.0010695187 | AT7: 0.0012 | AU7: 1.33
A8: 販売アイテム | B8: HOOD MUFFLER | C8: RUBBER RAIN BOOTS | D8: GBH HOME ERASER | E8: LONG APRON | F8: MERINOWOOL HIGHNECK CARDIGAN | G8: MERINOWOOL HIGHNECK CARDIGAN | I8: SMOCKED SHEER TOP | M8: UMBRELLA | O8: STAINLESS STEEL TISSUE CASE | P8: MERINOWOOL HIGHNECK CARDIGAN | Q8: TUMBLER POUCH | S8: MERINOWOOL HIGHNECK CARDIGAN | X8: KITCHEN CLOTH 3枚セット | Y8: HOOD MUFFLER | Z8: STAINLESS STEEL MINI TRAY | AA8: CERAMIC PLANT POT | AB8: STANDARD DRINKING GLASS
B9: HANDMADE BONNET | D9: STAINLESS STEEL TRAY | E9: GEL PEN | F9: ON THE ROCKS GLASS | G9: LONG APRON | I9: BUTTON CARDIGAN | O9: MERINOWOOL HIGHNECK CARDIGAN | P9: HANDMADE BONNET | Q9: TUMBLER POUCH | X9: REFILL TISSUE 10PACK | Z9: SQUARE CANDLE(S) | AA9: ON THE ROCKS GLASS
D10: DAILY LIP BALM CLEAR | E10: HAND CREAM | I10: POPUP POCKET PANTS | O10: MULTI POUCH | Q10: SQUARE CANDLE(L) | Z10: SQUARE ROOM SHOES
D11: MERINOWOOL HIGHNECK CARDIGAN | E11: SCENTED HAIR & BODY MIST DISCOVERY KIT | I11: MERINOWOOL HIGHNECK CARDIGAN | O11: MERINOWOOL HIGHNECK CARDIGAN
D12: DAILY HAND WASH | E12: MERINOWOOL HIGHNECK CARDIGAN | I12: 3-FOLDING UMBRELLA
I13: STAINLESS STEEL TUMBLER
E14: STAINLESS STEEL TRAY | I14: STAINLESS STEEL TISSUE CASE
A15: 広告 | B15: 1月カタル配信:35万 ・パートナーシップ20万 ・通常15万 | M15: 1月カタル配信:35万 ・パートナーシップ20万 ・通常15万 | W15: 1月カタル配信:35万 ・パートナーシップ20万 ・通常15万 | AG15: 1月カタル配信:35万 ・パートナーシップ20万 ・通常15万
A16: IG FOLLOWER
A17: KOL投稿有無
A18: 販促 | B18: 新年セール | C18: 新年セール | D18: 新年セール | E18: 新年セール | F18: 新年セール | G18: 新年セール | H18: 新年セール | I18: 新年セール | N18: 値下げ実施！
A20: 雑誌掲載

Sheet 2025.2
B1: 45687 | C1: 45688 | D1: 45689 | E1: 45690 | F1: 45691 | G1: 45692 | H1: 45693 | I1: 週締め | J1: 前週比 | K1: 45694 | L1: 45695 | M1: 45696 | N1: 45697 | O1: 45698 | P1: 45699 | Q1: 45700 | R1: 週締め | S1: 前週比 | T1: 45701 | U1: 45702 | V1: 45703 | W1: 45704 | X1: 45705 | Y1: 45706 | Z1: 45707 | AA1: 週締め | AB1: 前週比 | AC1: 45708 | AD1: 45709 | AE1: 45710 | AF1: 45711 | AG1: 45712 | AH1: 45713 | AI1: 45714 | AJ1: 週締め | AK1: 前週比 | AL1: 45715 | AM1: 45716 | AN1: 月締め | AO1: 先月比 | AP1: 当月KPI
B2: 木 | C2: 金 | D2: 土 | E2: 日 | F2: 月 | G2: 火 | H2: 水 | K2: 木 | L2: 金 | M2: 土 | N2: 日 | O2: 月 | P2: 火 | Q2: 水 | T2: 木 | U2: 金 | V2: 土 | W2: 日 | X2: 月 | Y2: 火 | Z2: 水 | AC2: 木 | AD2: 金 | AE2: 土 | AF2: 日 | AG2: 月 | AH2: 火 | AI2: 水 | AL2: 木 | AM2: 金
A3: 売り上げ | B3: 19200 | C3: 5100 | D3: 63000 | E3: 15400 | F3: 0 | G3: 0 | H3: 30550 | I3: =SUM(B3:H3) -> 133250 | J3: =I3/83600 -> 1.5938995 | K3: 12100 | L3: 40500 | M3: 15400 | N3: 15400 | O3: 0 | P3: 0 | Q3: 30800 | R3: =SUM(K3:Q3) -> 114200 | S3: =R3/I3 -> 0.85703565 | T3: 5100 | U3: 9800 | V3: 15850 | W3: 35300 | X3: 19000 | Y3: 0 | Z3: 0 | AA3: =SUM(T3:Z3) -> 85050 | AB3: =AA3/R3 -> 0.74474606 | AC3: 40800 | AD3: 10000 | AE3: 128500 | AF3: 20600 | AG3: 115200 | AH3: 52600 | AI3: 20500 | AJ3: =SUM(AC3:AI3) -> 388200 | AK3: =AJ3/AA3 -> 4.5643739 | AL3: 0 | AM3: 78800 | AN3: 865040
A4: 注文数（人数） | B4: 2 | C4: 1 | D4: 3 | E4: 1 | F4: 0 | G4: 0 | H4: 3 | I4: =SUM(B4:H4) -> 10 | J4: =I4/7 -> 1.4285714 | K4: 1 | L4: 3 | M4: 1 | N4: 1 | O4: 0 | P4: 0 | Q4: 1 | R4: =SUM(K4:Q4) -> 7 | S4: =R4/I4 -> 0.7 | T4: 1 | U4: 1 | V4: 2 | W4: 2 | X4: 1 | Y4: 0 | Z4: 0 | AA4: =SUM(T4:Z4) -> 7 | AB4: =AA4/R4 -> 1 | AC4: 4 | AD4: 2 | AE4: 5 | AF4: 2 | AG4: 9 | AH4: 3 | AI4: 2 | AJ4: =SUM(AC4:AI4) -> 27 | AK4: =AJ4/AA4 -> 3.8571429 | AL4: 0 | AM4: 5 | AN4: 53
A5: 客単価 | B5: =B3/B4 -> 9600 | C5: =C3/C4 -> 5100 | D5: =D3/D4 -> 21000 | E5: =E3/E4 -> 15400 | F5: 0 | G5: 0 | H5: =H3/H4 -> 10183.333 | I5: =AVERAGE(B5:H5) -> 8754.7619 | J5: =I5/8495 -> 1.0305782 | K5: =K3/K4 -> 12100 | L5: =L3/L4 -> 13500 | M5: =M3/M4 -> 15400 | N5: =N3/N4 -> 15400 | O5: 0 | P5: 0 | Q5: =Q3/Q4 -> 30800 | R5: =AVERAGE(K5,L5,M5,N5,Q5) -> 17440 | S5: =R5/I5 -> 1.9920587 | T5: =T3/T4 -> 5100 | U5: =U3/U4 -> 9800 | V5: =V3/V4 -> 7925 | W5: =W3/W4 -> 17650 | X5: =X3/X4 -> 19000 | Y5: 0 | Z5: 0 | AA5: =AVERAGE(T5:X5) -> 11895 | AB5: =AA5/R5 -> 0.68205275 | AC5: =AC3/AC4 -> 10200 | AD5: =AD3/AD4 -> 5000 | AE5: =AE3/AE4 -> 25700 | AF5: =AF3/AF4 -> 10300 | AG5: =AG3/AG4 -> 12800 | AH5: =AH3/AH4 -> 17533.333 | AI5: =AI3/AI4 -> 10250 | AJ5: =AVERAGE(AC5:AI5) -> 13111.905 | AK5: =AJ5/AA5 -> 1.1023039 | AL5: 0 | AM5: =AM3/AM4 -> 15760 | AN5: 14626
A6: セッション | B6: 981 | C6: 935 | D6: 305 | E6: 257 | F6: 171 | G6: 308 | H6: 363 | I6: =SUM(B6:H6) -> 3320 | J6: =I6/7122 -> 0.46616119 | K6: 406 | L6: 514 | M6: 190 | N6: 122 | O6: 142 | P6: 181 | Q6: 142 | R6: =SUM(K6:Q6) -> 1697 | S6: =R6/I6 -> 0.51114458 | T6: 186 | U6: 157 | V6: 450 | W6: 592 | X6: 781 | Y6: 731 | Z6: 658 | AA6: =SUM(T6:Z6) -> 3555 | AB6: =AA6/R6 -> 2.0948733 | AC6: 699 | AD6: 614 | AE6: 678 | AF6: 640 | AG6: 977 | AH6: 879 | AI6: 893 | AJ6: =SUM(AC6:AI6) -> 5380 | AK6: =AJ6/AA6 -> 1.5133615 | AL6: 1071 | AM6: 1063 | AN6: 14484
A7: CVR | B7: =B4/B6 -> 0.002038736 | C7: =C4/C6 -> 0.0010695187 | D7: =D4/D6 -> 0.0098360656 | E7: =E4/E6 -> 0.0038910506 | F7: =F4/F6 -> 0 | G7: =G4/G6 -> 0 | H7: =H4/H6 -> 0.0082644628 | I7: =AVERAGE(B7:H7) -> 0.0035856905 | J7: 3.59 | K7: =K4/K6 -> 0.0024630542 | L7: =L4/L6 -> 0.0058365759 | M7: =M4/M6 -> 0.0052631579 | N7: =N4/N6 -> 0.0081967213 | O7: =O4/O6 -> 0 | P7: =P4/P6 -> 0 | Q7: =Q4/Q6 -> 0.0070422535 | R7: =AVERAGE(K7:Q7) -> 0.0041145375 | S7: =R7/I7 -> 1.1474882 | T7: =T4/T6 -> 0.0053763441 | U7: =U4/U6 -> 0.0063694268 | V7: =V4/V6 -> 0.0044444444 | W7: =W4/W6 -> 0.0033783784 | X7: =X4/X6 -> 0.0012804097 | Y7: =Y4/Y6 -> 0 | Z7: =Z4/Z6 -> 0 | AA7: =AVERAGE(T7:X7) -> 0.0041698007 | AB7: =AA7/R7 -> 1.0134312 | AC7: =AC4/AC6 -> 0.0057224607 | AD7: =AD4/AD6 -> 0.003257329 | AE7: =AE4/AE6 -> 0.0073746313 | AF7: =AF4/AF6 -> 0.003125 | AG7: =AG4/AG6 -> 0.0092118731 | AH7: =AH4/AH6 -> 0.0034129693 | AI7: =AI4/AI6 -> 0.0022396417 | AJ7: =AVERAGE(AC7:AI7) -> 0.0049062721 | AK7: =AJ7/AA7 -> 1.1766203 | AL7: =AL4/AL6 -> 0 | AM7: =AM4/AM6 -> 0.0047036689 | AN7: 0.0035
A8: 販売アイテム | B8: MERINOWOOL HIGHNECK CARDIGAN | C8: 3-FOLDING UMBRELLA | D8: MERINOWOOL HIGHNECK CARDIGAN | E8: MERINOWOOL HIGHNECK CARDIGAN | H8: PUCKERING PANTS
B9: TOOTHBRUSH 5本セット | D9: Mock-neck pleats Cardigan | H9: MASKING TAPE
D10: TEXTURE RUG | H10: GBH HOME ERASER
H11: MASKING TAPE
H12: PUCKERING PANTS
A18: 広告 | G18: ⚫︎広告予算：50万 CV広告配信
A19: IG FOLLOWER
A20: KOL投稿有無
A21: 販促 | C21: 新作販売開始
A23: 雑誌掲載

Sheet 2025.3
B1: 45715 | C1: 45716 | D1: 45717 | E1: 45718 | F1: 45719 | G1: 45720 | H1: 45721 | I1: 週締め | J1: 前週比 | K1: 45722 | L1: 45723 | M1: 45724 | N1: 45725 | O1: 45726 | P1: 45727 | Q1: 45728 | R1: 週締め | S1: 前週比 | T1: 45729 | U1: 45730 | V1: 45731 | W1: 45732 | X1: 45733 | Y1: 45734 | Z1: 45735 | AA1: 週締め | AB1: 前週比 | AC1: 45736 | AD1: 45737 | AE1: 45738 | AF1: 45739 | AG1: 45740 | AH1: 45741 | AI1: 45742 | AJ1: 週締め | AK1: 前週比 | AL1: 45743 | AM1: 45744 | AN1: 45745 | AO1: 45746 | AP1: 45747 | AQ1: 月締め | AR1: 先月比 | AS1: 45748 | AT1: 45749 | AU1: 週締め | AV1: 前週比
B2: 木 | C2: 金 | D2: 土 | E2: 日 | F2: 月 | G2: 火 | H2: 水 | K2: 木 | L2: 金 | M2: 土 | N2: 日 | O2: 月 | P2: 火 | Q2: 水 | T2: 木 | U2: 金 | V2: 土 | W2: 日 | X2: 月 | Y2: 火 | Z2: 水 | AC2: 木 | AD2: 金 | AE2: 土 | AF2: 日 | AG2: 月 | AH2: 火 | AI2: 水 | AL2: 木 | AM2: 金 | AN2: 土 | AO2: 日 | AP2: 月 | AS2: 火 | AT2: 水
A3: 売り上げ | B3: 0 | C3: 78800 | D3: 12900 | E3: 17700 | F3: 15400 | G3: 0 | H3: 4700 | I3: =SUM(B3:H3) -> 129500 | J3: 0.29 | K3: 15400 | L3: 56700 | M3: 46900 | N3: 52100 | O3: 33300 | P3: 114700 | Q3: 76600 | R3: =SUM(K3:Q3) -> 395700 | S3: =R3/I3 -> 3.0555985 | T3: 65800 | U3: 5200 | V3: 9800 | W3: 0 | X3: 31900 | Y3: 27200 | Z3: 45500 | AA3: =SUM(T3:Z3) -> 185400 | AC3: 0 | AD3: 5100 | AE3: 5900 | AF3: 42900 | AG3: 5100 | AH3: 12000 | AI3: 8400 | AL3: 18200 | AM3: 35300 | AN3: 4700 | AO3: 0 | AP3: 17500 | AS3: 5100 | AT3: 0
A4: 注文数（人数） | B4: 0 | C4: 5 | D4: 2 | E4: 1 | F4: 1 | G4: 0 | H4: 1 | I4: =SUM(B4:H4) -> 10 | J4: 0.37 | K4: 1 | L4: 4 | M4: 4 | N4: 3 | O4: 3 | P4: 5 | Q4: 7 | R4: =SUM(K4:Q4) -> 27 | S4: =R4/I4 -> 2.7 | T4: 6 | U4: 1 | V4: 2 | W4: 0 | X4: 2 | Y4: 3 | Z4: 3 | AA4: =SUM(T4:Z4) -> 17 | AC4: 0 | AD4: 1 | AE4: 1 | AF4: 2 | AG4: 1 | AH4: 2 | AI4: 2 | AL4: 1 | AM4: 1 | AN4: 1 | AO4: 0 | AP4: 3 | AS4: 1 | AT4: 0
A5: 客単価 | B5: 0 | C5: =C3/C4 -> 15760 | D5: =D3/D4 -> 6450 | E5: =E3/E4 -> 17700 | F5: =F3/F4 -> 15400 | G5: 0 | H5: =H3/H4 -> 4700 | I5: =AVERAGE(C5,D5,E5,F5,H5) -> 12002 | J5: 0.72 | K5: =K3/K4 -> 15400 | L5: =L3/L4 -> 14175 | M5: =M3/M4 -> 11725 | N5: =N3/N4 -> 17366.667 | O5: =O3/O4 -> 11100 | P5: =P3/P4 -> 22940 | Q5: =Q3/Q4 -> 10942.857 | R5: =AVERAGE(K5:Q5) -> 14807.075 | S5: =R5/I5 -> 1.2337173 | T5: =T3/T4 -> 10966.667 | U5: =U3/U4 -> 5200 | V5: =V3/V4 -> 4900 | W5: 0 | X5: =X3/X4 -> 15950 | Y5: =Y3/Y4 -> 9066.6667 | Z5: =Z3/Z4 -> 15166.667 | AA5: =AVERAGE(T5,U5,V5,X5,Y5,Z5) -> 10208.333
A6: セッション | B6: 1071 | C6: 1063 | D6: 712 | E6: 216 | F6: 253 | G6: 253 | H6: 277 | I6: =SUM(B6:H6) -> 3845 | J6: 0.5 | K6: 162 | L6: 1548 | M6: 2684 | N6: 1446 | O6: 1256 | P6: 1052 | Q6: 1077 | R6: =SUM(K6:Q6) -> 9225 | S6: =R6/I6 -> 2.3992198 | T6: 786 | U6: 433 | V6: 392 | W6: 635 | X6: 507 | Y6: 455 | Z6: 558 | AA6: =SUM(T6:Z6) -> 3766
A7: CVR | B7: =B4/B6 -> 0 | C7: =C4/C6 -> 0.0047036689 | D7: =D4/D6 -> 0.0028089888 | E7: =E4/E6 -> 0.0046296296 | F7: =F4/F6 -> 0.0039525692 | G7: =G4/G6 -> 0 | H7: =H4/H6 -> 0.0036101083 | I7: =AVERAGE(C7,D7,E7,F7,H7) -> 0.0039409929 | J7: 1.13 | K7: =K4/K6 -> 0.0061728395 | L7: =L4/L6 -> 0.0025839793 | M7: =M4/M6 -> 0.001490313 | N7: =N4/N6 -> 0.0020746888 | O7: =O4/O6 -> 0.002388535 | P7: =P4/P6 -> 0.0047528517 | Q7: =Q4/Q6 -> 0.0064995357 | R7: =AVERAGE(K7:Q7) -> 0.0037089633 | S7: =R7/I7 -> 0.94112406 | T7: =T4/T6 -> 0.0076335878 | U7: =U4/U6 -> 0.0023094688 | V7: =V4/V6 -> 0.0051020408 | W7: =W4/W6 -> 0 | X7: =X4/X6 -> 0.0039447732 | Y7: =Y4/Y6 -> 0.0065934066 | Z7: =Z4/Z6 -> 0.0053763441 | AA7: =AVERAGE(T7,U7,V7,X7,Y7,Z7) -> 0.0051599369
A8: 販売アイテム
A18: 広告 | B18: 月50万予算配信中 | G18: ⚫︎広告予算：50万 CV広告配信
A19: IG FOLLOWER
A20: KOL投稿有無
A21: 販促 | C21: 新作販売開始
A23: 雑誌掲載

Sheet 2025.4
B1: 45748 | C1: 45749 | D1: 週締め | E1: 前週比 | F1: 45750 | G1: 45751 | H1: 45752 | I1: 45753 | J1: 45754 | K1: 45755 | L1: 45756 | M1: 週締め | N1: 前週比 | O1: 45757 | P1: 45758 | Q1: 45759 | R1: 45760 | S1: 45761 | T1: 45762 | U1: 45763 | V1: 週締め | W1: 前週比 | X1: 45764 | Y1: 45765 | Z1: 45766 | AA1: 45767 | AB1: 45768 | AC1: 45769 | AD1: 45770 | AE1: 週締め | AF1: 前週比 | AG1: 45771 | AH1: 45772 | AI1: 45773 | AJ1: 45774 | AK1: 45775 | AL1: 45776 | AM1: 45777 | AN1: 週締め | AO1: 前週比 | AP1: 月締め | AQ1: 先月比 | AV1: 前週比
B2: 火 | C2: 水 | F2: 木 | G2: 金 | H2: 土 | I2: 日 | J2: 月 | K2: 火 | L2: 水 | O2: 木 | P2: 金 | Q2: 土 | R2: 日 | S2: 月 | T2: 火 | U2: 水 | X2: 木 | Y2: 金 | Z2: 土 | AA2: 日 | AB2: 月 | AC2: 火 | AD2: 水 | AG2: 木 | AH2: 金 | AI2: 土 | AJ2: 日 | AK2: 月 | AL2: 火 | AM2: 水
A3: 売り上げ | B3: 5100 | C3: 0 | F3: 2300 | G3: 22800 | H3: 23100 | I3: 9000 | J3: 25500 | K3: 10400 | L3: 9800 | M3: =SUM(F3:L3) -> 102900 | O3: 32400 | P3: 28200 | Q3: 0 | R3: 26700 | S3: 45950 | T3: 24100 | U3: 23790 | V3: =SUM(O3:U3) -> 181140 | X3: 32490 | Y3: 19980 | Z3: 35280 | AA3: 75240 | AB3: 32040 | AC3: 9800 | AD3: 500 | AE3: 205330 | AF3: 1.13 | AG3: 22700 | AH3: 37000 | AI3: 0 | AJ3: 0 | AK3: 10600 | AL3: 29000 | AM3: 5100 | AN3: 104400 | AO3: 0.51 | AP3: 700007 | AQ3: 0.8
A4: 注文数（人数） | B4: 1 | C4: 0 | F4: 1 | G4: 2 | H4: 2 | I4: 2 | J4: 1 | K4: 1 | L4: 2 | M4: =SUM(F4:L4) -> 11 | O4: 2 | P4: 3 | Q4: 0 | R4: 2 | S4: 6 | T4: 6 | U4: 4 | V4: =SUM(O4:U4) -> 23 | X4: 4 | Y4: 2 | Z4: 3 | AA4: 6 | AB4: 7 | AC4: 2 | AD4: 1 | AE4: 25 | AF4: 1.09 | AG4: 2 | AH4: 4 | AI4: 0 | AJ4: 0 | AK4: 2 | AL4: 4 | AM4: 1 | AN4: 13 | AO4: 0.52 | AP4: 73 | AQ4: 1.14
A5: 客単価 | B5: =B3/B4 -> 5100 | C5: 0 | F5: =F3/F4 -> 2300 | G5: =G3/G4 -> 11400 | H5: =H3/H4 -> 11550 | I5: =I3/I4 -> 4500 | J5: =J3/J4 -> 25500 | K5: =K3/K4 -> 10400 | L5: =L3/L4 -> 4900 | M5: =AVERAGE(F5:L5) -> 10078.571 | O5: =O3/O4 -> 16200 | P5: =P3/P4 -> 9400 | Q5: 0 | R5: =R3/R4 -> 13350 | S5: =S3/S4 -> 7658.3333 | T5: =T3/T4 -> 4016.6667 | U5: =U3/U4 -> 5947.5 | V5: =V3/V4 -> 7875.6522 | X5: =X3/X4 -> 8122.5 | Y5: =Y3/Y4 -> 9990 | Z5: =Z3/Z4 -> 11760 | AA5: =AA3/AA4 -> 12540 | AB5: =AB3/AB4 -> 4577.1429 | AC5: =AC3/AC4 -> 4900 | AD5: =AD3/AD4 -> 500 | AE5: =AE3/AE4 -> 8213.2 | AF5: 1.04 | AG5: =AG3/AG4 -> 11350 | AH5: =AH3/AH4 -> 9250 | AI5: 0 | AJ5: 0 | AK5: =AK3/AK4 -> 5300 | AL5: =AL3/AL4 -> 7250 | AM5: 0 | AN5: 8031 | AO5: 0.98 | AP5: 8204 | AQ5: 0.67
A6: セッション | B6: 277 | C6: 389 | F6: 496 | G6: 394 | H6: 317 | I6: 329 | J6: 250 | K6: 302 | L6: 421 | M6: =SUM(F6:L6) -> 2509 | O6: 494 | P6: 447 | Q6: 460 | R6: 562 | S6: 1192 | T6: 1177 | U6: 616 | V6: =SUM(O6:U6) -> 4948 | X6: 1034 | Y6: 1037 | Z6: 1093 | AA6: 1147 | AB6: 949 | AC6: 820 | AD6: 803 | AE6: 6883 | AF6: 1.26 | AG6: 788 | AH6: 547 | AI6: 139 | AJ6: 134 | AK6: 125 | AL6: 976 | AM6: 630 | AN6: 3339 | AO6: 0.49 | AP6: 18847 | AQ6: 0.96
A7: CVR | B7: =B4/B6 -> 0.0036101083 | C7: =C4/C6 -> 0 | F7: =F4/F6 -> 0.002016129 | G7: =G4/G6 -> 0.0050761421 | H7: =H4/H6 -> 0.0063091483 | I7: =I4/I6 -> 0.0060790274 | J7: =J4/J6 -> 0.004 | K7: =K4/K6 -> 0.0033112583 | L7: =L4/L6 -> 0.0047505938 | M7: =M4/M6 -> 0.0043842168 | O7: =O4/O6 -> 0.004048583 | P7: =P4/P6 -> 0.0067114094 | Q7: =Q4/Q6 -> 0 | R7: =R4/R6 -> 0.0035587189 | S7: =S4/S6 -> 0.005033557 | T7: =T4/T6 -> 0.005097706 | U7: =U4/U6 -> 0.0064935065 | V7: =V4/V6 -> 0.0046483428 | X7: =X4/X6 -> 0.003868472 | Y7: =Y4/Y6 -> 0.0019286403 | Z7: =Z4/Z6 -> 0.0027447392 | AA7: =AA4/AA6 -> 0.0052310375 | AB7: =AB4/AB6 -> 0.0073761855 | AC7: =AC4/AC6 -> 0.0024390244 | AD7: =AD4/AD6 -> 0.00124533 | AE7: =AE4/AE6 -> 0.0036321371 | AF7: 0.86 | AG7: =AG4/AG6 -> 0.0025380711 | AH7: =AH4/AH6 -> 0.0073126143 | AI7: =AI4/AI6 -> 0 | AJ7: =AJ4/AJ6 -> 0 | AK7: =AK4/AK6 -> 0.016 | AL7: =AL4/AL6 -> 0.0040983607 | AM7: 0 | AN7: =AN4/AN6 -> 0.0038933813 | AO7: 1.07 | AP7: 0.39 | AQ7: 1.21
A8: IG FOLLOWER | V8: 7541 | AE8: 8039 | AF8: =AE8/V8 -> 1.066039 | AG8: 8078 | AH8: 8819 | AI8: 8125 | AJ8: 8126 | AK8: 8122 | AL8: 8150
A9: 販売アイテム
A19: 広告 | B19: 予算：50万 (CV広告/トラフィック広告) | I19: 予算：50万 (CV広告/トラフィック広告) | R19: 予算：50万 (CV広告/トラフィック広告)
A20: IG FOLLOWER
A21: KOL投稿有無
A22: 販促
A24: 雑誌掲載

Sheet 2025.5
B1: 45778 | C1: 45779 | D1: 45780 | E1: 45781 | F1: 45782 | G1: 45783 | H1: 45784 | I1: 週締め | J1: 前週比 | K1: 45785 | L1: 45786 | M1: 45787 | N1: 45788 | O1: 45789 | P1: 45790 | Q1: 45791 | R1: 週締め | S1: 前週比 | T1: 45792 | U1: 45793 | V1: 45794 | W1: 45795 | X1: 45796 | Y1: 45797 | Z1: 45798 | AA1: 週締め | AB1: 前週比 | AC1: 45799 | AD1: 45800 | AE1: 45801 | AF1: 45802 | AG1: 45803 | AH1: 45804 | AI1: 45805 | AJ1: 週締め | AK1: 前週比 | AL1: 45806 | AM1: 45807 | AN1: 45808 | AO1: 月締め | AP1: 先月比 | AV1: 前週比
B2: 木 | C2: 金 | D2: 土 | E2: 日 | F2: 月 | G2: 火 | H2: 水 | K2: 木 | L2: 金 | M2: 土 | N2: 日 | O2: 月 | P2: 火 | Q2: 水 | T2: 木 | U2: 金 | V2: 土 | W2: 日 | X2: 月 | Y2: 火 | Z2: 水 | AC2: 木 | AD2: 金 | AE2: 土 | AF2: 日 | AG2: 月 | AH2: 火 | AI2: 水 | AL2: 木 | AM2: 金 | AN2: 土
A3: 売り上げ | B3: 43890 | C3: 19140 | D3: 0 | E3: 2090 | F3: 26180 | G3: 20460 | H3: 23320 | I3: 135080 | J3: 1.1 | K3: 23980 | L3: 19580 | M3: 23320 | N3: 59950 | O3: 22220 | P3: 9790 | Q3: 10560 | R3: 169400 | S3: 1.25 | T3: 61710 | U3: 11110 | V3: 45705 | W3: 22880 | X3: 22550 | Y3: 5170 | Z3: 17820 | AA3: 186945 | AB3: 1.1 | AC3: 9240 | AD3: 25960 | AE3: 25685 | AF3: 25630 | AG3: 37290 | AH3: 9570 | AI3: 26290 | AJ3: 159665 | AK3: 0.85 | AL3: 50490 | AM3: 6380 | AN3: 41580 | AO3: 749540
A4: 注文数（人数） | B4: 3 | C4: 3 | D4: 0 | E4: 1 | F4: 3 | G4: 1 | H4: 2 | I4: 13 | J4: 1 | K4: 2 | L4: 1 | M4: 2 | N4: 4 | O4: 1 | P4: 1 | Q4: 1 | R4: 12 | S4: 0.92 | T4: 1 | U4: 1 | V4: 4 | W4: 3 | X4: 3 | Y4: 1 | Z4: 1 | AA4: 14 | AB4: 1.17 | AC4: 2 | AD4: 3 | AE4: 3 | AF4: 2 | AG4: 4 | AH4: 2 | AI4: 2 | AJ4: 18 | AK4: 1.29 | AL4: 5 | AM4: 1 | AN4: 4 | AO4: 67
A5: 客単価 | B5: =B3/B4 -> 14630 | C5: =C3/C4 -> 6380 | D5: 0 | E5: =E3/E4 -> 2090 | F5: =F3/F4 -> 8726.6667 | G5: =G3/G4 -> 20460 | H5: =H3/H4 -> 11660 | I5: 8854 | J5: 1.1 | K5: =K3/K4 -> 11990 | L5: =L3/L4 -> 19580 | M5: =M3/M4 -> 11660 | N5: =N3/N4 -> 14987.5 | O5: =O3/O4 -> 22220 | P5: =P3/P4 -> 9790 | Q5: =Q3/Q4 -> 10560 | R5: 12192 | S5: 1.38 | T5: =T3/T4 -> 61710 | U5: =U3/U4 -> 11110 | V5: =V3/V4 -> 11426.25 | W5: =W3/W4 -> 7626.6667 | X5: =X3/X4 -> 7516.6667 | Y5: =Y3/Y4 -> 5170 | Z5: =Z3/Z4 -> 17820 | AA5: 11539 | AB5: 0.95 | AC5: =AC3/AC4 -> 4620 | AD5: =AD3/AD4 -> 8653.3333 | AE5: =AE3/AE4 -> 8561.6667 | AF5: =AF3/AF4 -> 12815 | AG5: =AG3/AG4 -> 9322.5 | AH5: =AH3/AH4 -> 4785 | AI5: =AI3/AI4 -> 13145 | AJ5: 7442 | AK5: 0.64 | AL5: =AL3/AL4 -> 10098 | AM5: =AM3/AM4 -> 6380 | AN5: =AN3/AN4 -> 10395 | AO5: 9554
A6: セッション | B6: 173 | C6: 335 | D6: 154 | E6: 373 | F6: 355 | G6: 367 | H6: 344 | I6: 2101 | J6: 0.63 | K6: 378 | L6: 438 | M6: 481 | N6: 575 | O6: 504 | P6: 471 | Q6: 393 | R6: 3240 | S6: 1.54 | T6: 327 | U6: 313 | V6: 430 | W6: 438 | X6: 426 | Y6: 380 | Z6: 325 | AA6: 2639 | AB6: 0.81 | AC6: 609 | AD6: 877 | AE6: 1099 | AF6: 1251 | AG6: 1265 | AH6: 1475 | AI6: 1002 | AJ6: 7578 | AK6: 2.97 | AL6: 1470 | AM6: 1431 | AN6: 1552 | AO6: 20489
A7: CVR | B7: =B4/B6 -> 0.01734104 | C7: =C4/C6 -> 0.0089552239 | D7: =D4/D6 -> 0 | E7: =E4/E6 -> 0.0026809651 | F7: =F4/F6 -> 0.0084507042 | G7: =G4/G6 -> 0.0027247956 | H7: =H4/H6 -> 0.0058139535 | I7: 0.62 | J7: 1.59 | K7: =K4/K6 -> 0.0052910053 | L7: =L4/L6 -> 0.002283105 | M7: =M4/M6 -> 0.0041580042 | N7: =N4/N6 -> 0.0069565217 | O7: =O4/O6 -> 0.001984127 | P7: =P4/P6 -> 0.0021231423 | Q7: =Q4/Q6 -> 0.0025445293 | R7: 0.37 | S7: 0.6 | T7: =T4/T6 -> 0.003058104 | U7: =U4/U6 -> 0.0031948882 | V7: =V4/V6 -> 0.0093023256 | W7: =W4/W6 -> 0.0068493151 | X7: =X4/X6 -> 0.0070422535 | Y7: =Y4/Y6 -> 0.0026315789 | Z7: =Z4/Z6 -> 0.0030769231 | AA7: 0.53 | AB7: 1.43 | AC7: =AC4/AC6 -> 0.0032840722 | AD7: =AD4/AD6 -> 0.0034207526 | AE7: =AE4/AE6 -> 0.0027297543 | AF7: =AF4/AF6 -> 0.001598721 | AG7: =AG4/AG6 -> 0.0031620553 | AH7: =AH4/AH6 -> 0.0013559322 | AI7: =AI4/AI6 -> 0.001996008 | AJ7: 0.22 | AK7: 0.41 | AL7: =AL4/AL6 -> 0.0034013605 | AM7: =AM4/AM6 -> 0.00069881202 | AN7: =AN4/AN6 -> 0.0025773196 | AO7: 0.0032
A8: IG FOLLOWER
A9: 販売アイテム
A19: 広告 | B19: 予算：50万 (CV広告/トラフィック広告) | G19: 予算：50万 (CV広告/トラフィック広告) | P19: 予算：50万 (CV広告/トラフィック広告)
A20: IG FOLLOWER
A21: KOL投稿有無
A22: 販促
A24: 雑誌掲載

Sheet 2025.6
B1: 45806 | C1: 45807 | D1: 45808 | E1: 45809 | F1: 45810 | G1: 45811 | H1: 45812 | I1: 週締め | J1: 前週比 | K1: 45813 | L1: 45814 | M1: 45815 | N1: 45816 | O1: 45817 | P1: 45818 | Q1: 45819 | R1: 週締め | S1: 前週比 | T1: 45820 | U1: 45821 | V1: 45822 | W1: 45823 | X1: 45824 | Y1: 45825 | Z1: 45826 | AA1: 週締め | AB1: 前週比 | AC1: 45827 | AD1: 45828 | AE1: 45829 | AF1: 45830 | AG1: 45831 | AH1: 45832 | AI1: 45833 | AJ1: 週締め | AK1: 前週比 | AL1: 45834 | AM1: 45835 | AN1: 45836 | AO1: 45837 | AP1: 45838 | AQ1: 月締め | AR1: 先月比 | AV1: 前週比
B2: 木 | C2: 金 | D2: 土 | E2: 日 | F2: 月 | G2: 火 | H2: 水 | K2: 木 | L2: 金 | M2: 土 | N2: 日 | O2: 月 | P2: 火 | Q2: 水 | T2: 木 | U2: 金 | V2: 土 | W2: 日 | X2: 月 | Y2: 火 | Z2: 水 | AC2: 木 | AD2: 金 | AE2: 土 | AF2: 日 | AG2: 月 | AH2: 火 | AI2: 水 | AL2: 木 | AM2: 金 | AN2: 土 | AO2: 日 | AP2: 月
A3: 売り上げ | B3: 50490 | C3: 6380 | D3: 41580 | E3: 146520 | F3: 0 | G3: 14080 | H3: 21450 | I3: =SUM(B3:H3) -> 280500 | J3: 1.76 | K3: 7920 | L3: 17600 | M3: 31350 | N3: 20680 | O3: -2090 | P3: 19470 | Q3: 16720 | R3: 111650 | S3: 0.4 | T3: 36960 | U3: 0 | V3: 0 | W3: 0 | X3: 24200 | Y3: 6490 | Z3: 8470 | AA3: 76120 | AB3: 0.77 | AC3: 27610 | AD3: 22000 | AE3: 6380 | AF3: 33440 | AG3: 81620 | AH3: 11110 | AI3: -4400 | AJ3: 177760 | AK3: 2.34 | AL3: 0 | AM3: 6380 | AN3: 32010 | AO3: 0 | AP3: 53339 | AQ3: 626219 | AR3: 0.84
A4: 注文数（人数） | B4: 5 | C4: 1 | D4: 4 | E4: 8 | F4: 0 | G4: 1 | H4: 2 | I4: =SUM(B4:H4) -> 21 | J4: 1.17 | K4: 1 | L4: 2 | M4: 2 | N4: 1 | O4: 0 | P4: 2 | Q4: 2 | R4: 10 | S4: 0.48 | T4: 2 | U4: 0 | V4: 0 | W4: 0 | X4: 2 | Y4: 1 | Z4: 2 | AA4: 7 | AB4: 0.7 | AC4: 4 | AD4: 3 | AE4: 1 | AF4: 2 | AG4: 10 | AH4: 3 | AI4: 0 | AJ4: 23 | AK4: 3.29 | AL4: 0 | AM4: 1 | AN4: 3 | AO4: 0 | AP4: 2 | AQ4: 57 | AR4: 0.85
A5: 客単価 | B5: =B3/B4 -> 10098 | C5: =C3/C4 -> 6380 | D5: =D3/D4 -> 10395 | E5: =E3/E4 -> 18315 | F5: 0 | G5: =G3/G4 -> 14080 | H5: =H3/H4 -> 10725 | I5: =I3/I4 -> 13357.143 | J5: 1.55 | K5: =K3/K4 -> 7920 | L5: =L3/L4 -> 8800 | M5: =M3/M4 -> 15675 | N5: =N3/N4 -> 20680 | O5: 0 | P5: =P3/P4 -> 9735 | Q5: =Q3/Q4 -> 8360 | R5: =R3/R4 -> 11165 | S5: 0.85 | T5: =T3/T4 -> 18480 | U5: 0 | V5: 0 | W5: 0 | X5: =X3/X4 -> 12100 | Y5: =Y3/Y4 -> 6490 | Z5: =Z3/Z4 -> 4235 | AA5: 9286 | AB5: 0.94 | AC5: =AC3/AC4 -> 6902.5 | AD5: =AD3/AD4 -> 7333.3333 | AE5: =AE3/AE4 -> 6380 | AF5: =AF3/AF4 -> 16720 | AG5: =AG3/AG4 -> 8162 | AH5: =AH3/AH4 -> 3703.3333 | AI5: =AI3/AI4 -> #DIV/0! | AJ5: =AJ3/AJ4 -> 7728.6957 | AK5: 0.81 | AL5: =AL3/AL4 -> #DIV/0! | AM5: =AM3/AM4 -> 6380 | AN5: =AN3/AN4 -> 10670 | AO5: =AO3/AO4 -> #DIV/0! | AP5: =AP3/AP4 -> 26669.5 | AQ5: 10095 | AR5: 1.06
A6: セッション | B6: 1470 | C6: 1431 | D6: 1552 | E6: 426 | F6: 448 | G6: 511 | H6: 474 | I6: =SUM(B6:H6) -> 6312 | J6: 0.77 | K6: 406 | L6: 440 | M6: 480 | N6: 510 | O6: 486 | P6: 583 | Q6: 479 | R6: 3384 | S6: 0.54 | T6: 696 | U6: 318 | V6: 112 | W6: 139 | X6: 119 | Y6: 706 | Z6: 756 | AA6: 2846 | AB6: 0.84 | AC6: 782 | AD6: 663 | AE6: 886 | AF6: 857 | AG6: 828 | AH6: 708 | AI6: 657 | AJ6: 5381 | AK6: 1.88 | AL6: 629 | AM6: 599 | AN6: 651 | AO6: 663 | AP6: 649 | AQ6: 16677 | AR6: 0.81
A7: CVR | B7: =B4/B6 -> 0.0034013605 | C7: =C4/C6 -> 0.00069881202 | D7: =D4/D6 -> 0.0025773196 | E7: =E4/E6 -> 0.018779343 | F7: =F4/F6 -> 0 | G7: =G4/G6 -> 0.0019569472 | H7: =H4/H6 -> 0.0042194093 | I7: =I4/I6 -> 0.0033269962 | J7: 1.35 | K7: =K4/K6 -> 0.0024630542 | L7: =L4/L6 -> 0.0045454545 | M7: =M4/M6 -> 0.0041666667 | N7: =N4/N6 -> 0.0019607843 | O7: =O4/O6 -> 0 | P7: =P4/P6 -> 0.0034305317 | Q7: =Q4/Q6 -> 0.0041753653 | R7: =R4/R6 -> 0.0029550827 | S7: 0.98 | T7: =T4/T6 -> 0.0028735632 | U7: =U4/U6 -> 0 | V7: =V4/V6 -> 0 | W7: =W4/W6 -> 0 | X7: =X4/X6 -> 0.016806723 | Y7: =Y4/Y6 -> 0.0014164306 | Z7: =Z4/Z6 -> 0.0026455026 | AA7: =AA4/AA6 -> 0.0024595924 | AB7: 0.83 | AC7: =AC4/AC6 -> 0.0051150895 | AD7: =AD4/AD6 -> 0.0045248869 | AE7: =AE4/AE6 -> 0.0011286682 | AF7: =AF4/AF6 -> 0.0023337223 | AG7: =AG4/AG6 -> 0.012077295 | AH7: =AH4/AH6 -> 0.0042372881 | AI7: =AI4/AI6 -> 0 | AJ7: =AJ4/AJ6 -> 0.0042742985 | AK7: 1.75 | AL7: =AL4/AL6 -> 0 | AM7: =AM4/AM6 -> 0.0016694491 | AN7: =AN4/AN6 -> 0.0046082949 | AO7: =AO4/AO6 -> 0 | AP7: =AP4/AP6 -> 0.0030816641 | AQ7: 0.0034 | AR7: 1.04
A8: IG FOLLOWER | AA8: 8833 | AQ8: 9100
A9: 広告 | B9: 予算：50万 (CV広告/トラフィック広告) | G9: 予算：50万 (CV広告/トラフィック広告) | P9: 予算：50万 (CV広告/トラフィック広告)
A10: 販促 | B10: --- | C10: --- | D10: --- | E10: --- | F10: --- | G10: --- | H10: --- | I10: --- | J10: --- | K10: --- | L10: VALLANコスメ協賛 | M10: VALLANコスメ協賛 | N10: VALLANコスメ協賛 | O10: --- | P10: --- | Q10: 新作傘発売
B11: --- | C11: --- | D11: --- | E11: --- | F11: --- | G11: --- | H11: --- | I11: --- | J11: --- | K11: --- | L11: --- | M11: --- | N11: --- | O11: --- | P11: --- | Q11: ---
A12: 雑誌掲載
A13: KOL投稿有無

Sheet 2025.7
B1: 45834 | C1: 45835 | D1: 45836 | E1: 45837 | F1: 45838 | G1: 45839 | H1: 45840 | I1: 週締め | J1: 前週比 | K1: 45841 | L1: 45842 | M1: 45843 | N1: 45844 | O1: 45845 | P1: 45846 | Q1: 45847 | R1: 週締め | S1: 前週比 | T1: 45848 | U1: 45849 | V1: 45850 | W1: 45851 | X1: 45852 | Y1: 45853 | Z1: 45854 | AA1: 週締め | AB1: 前週比 | AC1: 45855 | AD1: 45856 | AE1: 45857 | AF1: 45858 | AG1: 45859 | AH1: 45860 | AI1: 45861 | AJ1: 週締め | AK1: 前週比 | AL1: 45862 | AM1: 45863 | AN1: 45864 | AO1: 45865 | AP1: 45866 | AQ1: 45867 | AR1: 45868 | AS1: 45869 | AT1: 月締め | AU1: 先月比 | AV1: 前週比
B2: 木 | C2: 金 | D2: 土 | E2: 日 | F2: 月 | G2: 火 | H2: 水 | K2: 木 | L2: 金 | M2: 土 | N2: 日 | O2: 月 | P2: 火 | Q2: 水 | T2: 木 | U2: 金 | V2: 土 | W2: 日 | X2: 月 | Y2: 火 | Z2: 水 | AC2: 木 | AD2: 金 | AE2: 土 | AF2: 日 | AG2: 月 | AH2: 火 | AI2: 水 | AL2: 木 | AM2: 金 | AN2: 土 | AO2: 日 | AP2: 月 | AQ2: 火 | AR2: 水 | AS2: 木
A3: 売り上げ | B3: 0 | C3: 6380 | D3: 32010 | E3: 0 | F3: 53339 | G3: 4928 | H3: 102718 | I3: 199375 | J3: 1.12 | K3: 44484 | L3: 16390 | M3: 36289 | N3: 59543 | O3: 0 | P3: 33000 | Q3: 13475 | R3: 203181 | S3: 1.019 | T3: 11000 | U3: 21450 | V3: 11990 | W3: 29260 | X3: 31460 | Y3: 2860 | Z3: 24112 | AA3: 132132 | AB3: 0.65 | AC3: 0 | AD3: 0 | AE3: 43340 | AF3: 0 | AG3: 11330 | AH3: 11330 | AI3: 53460 | AJ3: 119460 | AK3: 0.9 | AL3: 9240 | AM3: 27742 | AN3: 37180 | AO3: 22110 | AP3: 22880 | AQ3: 5060 | AR3: 21362 | AS3: 2860 | AT3: 683683 | AU3: 1.09
A4: 注文数（人数） | B4: 0 | C4: 1 | D4: 3 | E4: 0 | F4: 2 | G4: 1 | H4: 5 | I4: 12 | J4: 0.52 | K4: 4 | L4: 2 | M4: 3 | N4: 7 | O4: 0 | P4: 2 | Q4: 2 | R4: 20 | S4: 1.67 | T4: 1 | U4: 3 | V4: 1 | W4: 3 | X4: 3 | Y4: 1 | Z4: 3 | AA4: 15 | AB4: 0.85 | AC4: 0 | AD4: 0 | AE4: 3 | AF4: 0 | AG4: 2 | AH4: 1 | AI4: 2 | AJ4: 8 | AK4: 0.53 | AL4: 2 | AM4: 2 | AN4: 5 | AO4: 3 | AP4: 1 | AQ4: 1 | AR4: 1 | AS4: 1 | AT4: 65 | AU4: 1.14
A5: 客単価 | B5: =B3/B4 -> #DIV/0! | C5: =C3/C4 -> 6380 | D5: =D3/D4 -> 10670 | E5: =E3/E4 -> #DIV/0! | F5: =F3/F4 -> 26669.5 | G5: =G3/G4 -> 4928 | H5: =H3/H4 -> 20543.6 | I5: =I3/I4 -> 16614.583 | J5: 1.95 | K5: 11121 | L5: 8195 | M5: 12096 | N5: 8506 | O5: 0 | P5: 16500 | Q5: 6737 | R5: =R3/R4 -> 10159.05 | S5: 0.611 | T5: 11000 | U5: 7150 | V5: 11990 | W5: 9753 | X5: 10486 | Y5: 2860 | Z5: =Z3/Z4 -> 8037.3333 | AA5: =AA3/AA4 -> 8808.8 | AB5: 0.86 | AC5: 0 | AD5: 0 | AE5: =AE3/AE4 -> 14446.667 | AF5: 0 | AG5: =AG3/AG4 -> 5665 | AH5: 11330 | AI5: =AI3/AI4 -> 26730 | AJ5: =AJ3/AJ4 -> 14932.5 | AK5: 1.695 | AL5: =AL3/AL4 -> 4620 | AM5: =AM3/AM4 -> 13871 | AN5: =AN3/AN4 -> 7436 | AO5: =AO3/AO4 -> 7370 | AP5: =AP3/AP4 -> 22880 | AQ5: 5060 | AR5: 21362 | AS5: 2860 | AT5: =AT3/AT4 -> 10518.2 | AU5: 1.04
A6: セッション | B6: 629 | C6: 599 | D6: 651 | E6: 663 | F6: 649 | G6: 447 | H6: 365 | I6: 4003 | J6: 0.78 | K6: 431 | L6: 411 | M6: 393 | N6: 589 | O6: 517 | P6: 441 | Q6: 406 | R6: 3188 | S6: 0.88 | T6: 409 | U6: 312 | V6: 388 | W6: 447 | X6: 400 | Y6: 482 | Z6: 424 | AA6: 2862 | AB6: 0.9 | AC6: 347 | AD6: 378 | AE6: 405 | AF6: 402 | AG6: 456 | AH6: 399 | AI6: 487 | AJ6: 2874 | AK6: 1.004 | AL6: 492 | AM6: 401 | AN6: 501 | AO6: 597 | AP6: 467 | AQ6: 504 | AR6: 452 | AS6: 448 | AT6: 13703 | AU6: 0.83
A7: CVR | B7: =B4/B6 -> 0 | C7: =C4/C6 -> 0.0016694491 | D7: =D4/D6 -> 0.0046082949 | E7: =E4/E6 -> 0 | F7: =F4/F6 -> 0.0030816641 | G7: =G4/G6 -> 0.0022371365 | H7: =H4/H6 -> 0.01369863 | I7: =I4/I6 -> 0.0029977517 | J7: 0.67 | K7: 0.0116 | L7: 0.0024 | M7: 0.0076 | N7: 0.0119 | O7: 0 | P7: 0.0045 | Q7: 0.0049 | R7: 0.63 | S7: 2.15 | T7: 0.0024 | U7: 0.0096 | V7: 0.0026 | W7: 0.0067 | X7: 0.005 | Y7: 0.0021 | Z7: 0.0071 | AA7: 0.0049 | AB7: 0.78 | AC7: 0 | AD7: 0 | AE7: 0.0074 | AF7: 0 | AG7: 0.0044 | AH7: 0.0025 | AI7: 0.0041 | AJ7: 0.0028 | AK7: 0.57 | AL7: 0.0041 | AM7: 0.005 | AN7: 0.01 | AO7: 0.005 | AP7: 0.0021 | AQ7: 0.002 | AR7: 0.22 | AS7: 0.0022 | AT7: 0.0047 | AU7: 1.39
A8: IG FOLLOWER | F8: SALE ミッドシーズンセール | G8: SALE ミッドシーズンセール | H8: SALE ミッドシーズンセール | I8: SALE ミッドシーズンセール | J8: SALE ミッドシーズンセール | K8: SALE ミッドシーズンセール | L8: SALE ミッドシーズンセール | M8: SALE ミッドシーズンセール | N8: SALE ミッドシーズンセール
A9: 販売アイテム
A19: 広告 | B19: 予算：50万 (CV広告/トラフィック広告) | G19: 予算：50万 (CV広告/トラフィック広告) | P19: 予算：50万 (CV広告/トラフィック広告) | AL19: 公式LINE運用開始
A20: IG FOLLOWER
A21: KOL投稿有無
A22: 販促
A24: 雑誌掲載

Sheet 2025.8
B1: 45869 | C1: 45870 | D1: 45871 | E1: 45872 | F1: 45873 | G1: 45874 | H1: 45875 | I1: 週締め | J1: 前週比 | K1: 45876 | L1: 45877 | M1: 45878 | N1: 45879 | O1: 45880 | P1: 45881 | Q1: 45882 | R1: 週締め | S1: 前週比 | T1: 45883 | U1: 45884 | V1: 45885 | W1: 45886 | X1: 45887 | Y1: 45888 | Z1: 45889 | AA1: 週締め | AB1: 前週比 | AC1: 45890 | AD1: 45891 | AE1: 45892 | AF1: 45893 | AG1: 45894 | AH1: 45895 | AI1: 45896 | AJ1: 週締め | AK1: 前週比 | AL1: 45897 | AM1: 45898 | AN1: 45899 | AO1: 45900 | AP1: 月締め | AQ1: 先月比
B2: 木 | C2: 金 | D2: 土 | E2: 日 | F2: 月 | G2: 火 | H2: 水 | K2: 木 | L2: 金 | M2: 土 | N2: 日 | O2: 月 | P2: 火 | Q2: 水 | T2: 木 | U2: 金 | V2: 土 | W2: 日 | X2: 月 | Y2: 火 | Z2: 水 | AC2: 木 | AD2: 金 | AE2: 土 | AF2: 日 | AG2: 月 | AH2: 火 | AI2: 水 | AL2: 木 | AM2: 金 | AN2: 土 | AO2: 日
A3: 売り上げ | B3: 2860 | C3: 5819 | D3: 6380 | E3: 4037 | F3: 2860 | G3: 23320 | H3: 35244 | I3: 80520 | J3: 0.68 | K3: 3300 | L3: 15565 | M3: 38742 | N3: 32153 | O3: 39380 | P3: 11990 | Q3: 45001 | R3: 186131 | S3: 2.31 | T3: 2552 | U3: 35673 | V3: 22759 | W3: 10208 | X3: 16940 | Y3: 7458 | Z3: 18810 | AA3: 99484 | AB3: 0.53 | AC3: 0 | AD3: 48378 | AE3: 40689 | AF3: 0 | AG3: 50589 | AH3: 81202 | AI3: 21703 | AJ3: 242561 | AK3: 1.68 | AL3: 65824 | AM3: 17952 | AN3: 35079 | AO3: 44264 | AP3: 765831 | AQ3: 1.12
A4: 注文数（人数） | B4: 1 | C4: 1 | D4: 1 | E4: 1 | F4: 1 | G4: 3 | H4: 3 | I4: 11 | J4: 0.73 | K4: 1 | L4: 2 | M4: 3 | N4: 5 | O4: 2 | P4: 1 | Q4: 4 | R4: 18 | S4: 1.64 | T4: 1 | U4: 3 | V4: 2 | W4: 2 | X4: 1 | Y4: 2 | Z4: 2 | AA4: 13 | AB4: 0.72 | AC4: 0 | AD4: 4 | AE4: 3 | AF4: 0 | AG4: 5 | AH4: 9 | AI4: 2 | AJ4: 23 | AK4: 1.35 | AL4: 6 | AM4: 2 | AN4: 4 | AO4: 6 | AP4: 82 | AQ4: 1.26
A5: 客単価 | B5: =B3/B4 -> 2860 | C5: =C3/C4 -> 5819 | D5: =D3/D4 -> 6380 | E5: =E3/E4 -> 4037 | F5: =F3/F4 -> 2860 | G5: =G3/G4 -> 7773.3333 | H5: =H3/H4 -> 11748 | I5: =I3/I4 -> 7320 | J5: 0.91 | K5: =K3/K4 -> 3300 | L5: =L3/L4 -> 7782.5 | M5: =M3/M4 -> 12914 | N5: =N3/N4 -> 6430.6 | O5: =O3/O4 -> 19690 | P5: =P3/P4 -> 11990 | Q5: =Q3/Q4 -> 11250.25 | R5: =R3/R4 -> 10340.611 | S5: 1.41 | T5: =T3/T4 -> 2552 | U5: =U3/U4 -> 11891 | V5: =V3/V4 -> 11379.5 | W5: =W3/W4 -> 5104 | X5: =X3/X4 -> 16940 | Y5: =Y3/Y4 -> 3729 | Z5: =Z3/Z4 -> 9405 | AA5: =AA3/AA4 -> 7652.6154 | AB5: 0.74 | AC5: 0 | AD5: =AD3/AD4 -> 12094.5 | AE5: =AE3/AE4 -> 13563 | AF5: 0 | AG5: =AG3/AG4 -> 10117.8 | AH5: =AH3/AH4 -> 9022.4444 | AI5: =AI3/AI4 -> 10851.5 | AJ5: =AJ3/AJ4 -> 10546.13 | AK5: 1.37 | AL5: =AL3/AL4 -> 10970.667 | AM5: =AM3/AM4 -> 8976 | AN5: =AN3/AN4 -> 8769.75 | AO5: =AO3/AO4 -> 7377.3333 | AP5: =AP3/AP4 -> 9339.4024 | AQ5: 0.887
A6: セッション | B6: 448 | C6: 885 | D6: 221 | E6: 191 | F6: 385 | G6: 540 | H6: 473 | I6: 3143 | J6: 0.92 | K6: 509 | L6: 413 | M6: 494 | N6: 473 | O6: 537 | P6: 501 | Q6: 445 | R6: 3372 | S6: 1.07 | T6: 360 | U6: 324 | V6: 297 | W6: 327 | X6: 364 | Y6: 459 | Z6: 488 | AA6: 2619 | AB6: 0.88 | AC6: 373 | AD6: 354 | AE6: 405 | AF6: 431 | AG6: 438 | AH6: 535 | AI6: 781 | AJ6: 3317 | AK6: 1.08 | AL6: 698 | AM6: 496 | AN6: 547 | AO6: 492 | AP6: 14236 | AQ6: 1.04
A7: CVR | B7: 0.0022 | C7: 0.0011 | D7: 0.0045 | E7: 0.0052 | F7: 0.0026 | G7: 0.0056 | H7: 0.0063 | I7: 0.0035 | J7: 0.8 | K7: 0.002 | L7: 0.0048 | M7: 0.0061 | N7: 0.0063 | O7: 0.0037 | P7: 0.002 | Q7: 0.009 | R7: 0.0047 | S7: 1.36 | T7: 0.0028 | U7: 0.0093 | V7: 0.0067 | W7: 0.0061 | X7: 0.0027 | Y7: 0.0044 | Z7: 0.002 | AA7: 0.0046 | AB7: 0.97 | AC7: 0 | AD7: 0.0085 | AE7: 0.0074 | AF7: 0 | AG7: 0.0137 | AH7: 0.015 | AI7: 0.0026 | AJ7: 0.0066 | AK7: 1.27 | AL7: 0.0086 | AM7: 0.004 | AN7: 0.0073 | AO7: 0.0122 | AP7: 0.0055 | AQ7: 1.17
A8: IG FOLLOWER
A9: 販売アイテム
A19: 広告
A20: IG FOLLOWER
A21: KOL投稿有無
A22: 販促
A24: 雑誌掲載

Sheet 2025.9
B1: 45897 | C1: 45898 | D1: 45899 | E1: 45900 | F1: 45901 | G1: 45902 | H1: 45903 | I1: 週締め | J1: 前週比 | K1: 45904 | L1: 45905 | M1: 45906 | N1: 45907 | O1: 45908 | P1: 45909 | Q1: 45910 | R1: 週締め | S1: 前週比 | T1: 45911 | U1: 45912 | V1: 45913 | W1: 45914 | X1: 45915 | Y1: 45916 | Z1: 45917 | AA1: 週締め | AB1: 前週比 | AC1: 45918 | AD1: 45919 | AE1: 45920 | AF1: 45921 | AG1: 45922 | AH1: 45923 | AI1: 45924 | AJ1: 週締め | AK1: 前週比 | AL1: 45925 | AM1: 45926 | AN1: 45927 | AO1: 45928 | AP1: 45929 | AQ1: 45930
B2: 木 | C2: 金 | D2: 土 | E2: 日 | F2: 月 | G2: 火 | H2: 水 | K2: 木 | L2: 金 | M2: 土 | N2: 日 | O2: 月 | P2: 火 | Q2: 水 | T2: 木 | U2: 金 | V2: 土 | W2: 日 | X2: 月 | Y2: 火 | Z2: 水 | AC2: 木 | AD2: 金 | AE2: 土 | AF2: 日 | AG2: 月 | AH2: 火 | AI2: 水 | AL2: 木 | AM2: 金 | AN2: 土 | AO2: 日 | AP2: 月 | AQ2: 火
A3: 売り上げ | B3: 65824 | C3: 17952 | D3: 35079 | E3: 44264 | F3: 48048 | G3: 5819 | H3: 56232 | I3: 273218 | J3: 1.14 | K3: 62436 | L3: 40403 | M3: 71577 | N3: 47377 | O3: 32373 | P3: 24233 | Q3: 6380 | R3: 284779 | S3: 1.05 | T3: 23540 | U3: 0 | V3: 30217 | W3: 20592 | X3: 84927 | Y3: 227270 | Z3: 95289 | AA3: 481835 | AB3: 1.74 | AC3: 44933 | AD3: 37523 | AE3: 98496 | AF3: 104978 | AG3: 0 | AH3: 12661 | AI3: 0 | AJ3: 298591 | AK3: 0.62 | AL3: 13826 | AM3: 2750 | AN3: 5280 | AO3: 74800 | AP3: 0 | AQ3: 153010
A4: 注文数（人数） | B4: 6 | C4: 2 | D4: 4 | E4: 6 | F4: 4 | G4: 1 | H4: 4 | I4: 27 | J4: 1.17 | K4: 6 | L4: 4 | M4: 6 | N4: 4 | O4: 3 | P4: 2 | Q4: 1 | R4: 26 | S4: 0.96 | T4: 3 | U4: 0 | V4: 5 | W4: 1 | X4: 11 | Y4: 12 | Z4: 11 | AA4: 43 | AB4: 1.65 | AC4: 6 | AD4: 6 | AE4: 10 | AF4: 10 | AG4: 0 | AH4: 3 | AI4: 0 | AJ4: 35 | AK4: 0.81 | AL4: 2 | AM4: 1 | AN4: 1 | AO4: 2 | AP4: 0 | AQ4: 5
A5: 客単価 | B5: =B3/B4 -> 10970.667 | C5: =C3/C4 -> 8976 | D5: =D3/D4 -> 8769.75 | E5: =E3/E4 -> 7377.3333 | F5: =F3/F4 -> 12012 | G5: =G3/G4 -> 5819 | H5: =H3/H4 -> 14058 | I5: =I3/I4 -> 10119.185 | J5: 0.97 | K5: =K3/K4 -> 10406 | L5: =L3/L4 -> 10100.75 | M5: =M3/M4 -> 11929.5 | N5: =N3/N4 -> 11844.25 | O5: =O3/O4 -> 10791 | P5: =P3/P4 -> 12116.5 | Q5: =Q3/Q4 -> 6380 | R5: =R3/R4 -> 10953.038 | S5: 1.08 | T5: =T3/T4 -> 7846.6667 | U5: 0 | V5: =V3/V4 -> 6043.4 | W5: =W3/W4 -> 20592 | X5: =X3/X4 -> 7720.6364 | Y5: =Y3/Y4 -> 18939.167 | Z5: =Z3/Z4 -> 8662.6364 | AA5: =AA3/AA4 -> 11205.465 | AB5: 1.024 | AC5: =AC3/AC4 -> 7488.8333 | AD5: =AD3/AD4 -> 6253.8333 | AE5: =AE3/AE4 -> 9849.6 | AF5: =AF3/AF4 -> 10497.8 | AG5: 0 | AH5: =AH3/AH4 -> 4220.3333 | AI5: 0 | AJ5: =AJ3/AJ4 -> 8531.1714 | AK5: 0.76 | AL5: =AL3/AL4 -> 6913 | AM5: =AM3/AM4 -> 2750 | AN5: =AN3/AN4 -> 5280 | AO5: =AO3/AO4 -> 37400 | AP5: 0 | AQ5: =AQ3/AQ4 -> 30602
A6: セッション | B6: 698 | C6: 496 | D6: 547 | E6: 492 | F6: 458 | G6: 405 | H6: 391 | I6: 3487 | J6: 1.05 | K6: 330 | L6: 341 | M6: 320 | N6: 334 | O6: 355 | P6: 323 | Q6: 327 | R6: 2330 | S6: 0.77 | T6: 309 | U6: 310 | V6: 356 | W6: 324 | X6: 483 | Y6: 453 | Z6: 424 | AA6: 2659 | AB6: 1.14 | AC6: 405 | AD6: 537 | AE6: 565 | AF6: 584 | AG6: 372 | AH6: 317 | AI6: 276 | AJ6: 3056 | AK6: 1.15 | AL6: 311 | AM6: 371 | AN6: 336 | AO6: 840 | AP6: 810 | AQ6: 759
A7: CVR | B7: 0.0086 | C7: 0.004 | D7: 0.0073 | E7: 0.0122 | F7: 0.0066 | G7: 0.0025 | H7: 0.0102 | I7: 0.0075 | J7: 1.12 | K7: 0.0182 | L7: 0.0117 | M7: 0.0156 | N7: 0.012 | O7: 0.0085 | P7: 0.0062 | Q7: 0.0031 | R7: 0.0107 | S7: 1.44 | T7: 0.0097 | U7: 0 | V7: 0.0084 | W7: 0.0031 | X7: 0.0228 | Y7: 0.0243 | Z7: 0.0259 | AA7: 0.015 | AB7: 1.4 | AC7: 0.0148 | AD7: 0.0112 | AE7: 0.0177 | AF7: 0.0154 | AG7: 0 | AH7: 0.0095 | AI7: 0 | AJ7: 0.0111 | AK7: 0.74 | AL7: 0.0064 | AM7: 0.0027 | AN7: 0.003 | AO7: 0.0024 | AP7: 0 | AQ7: 0.0053
A8: IG FOLLOWER
A9: 販売アイテム
A19: 広告
A20: KOL投稿有無
A21: 販促
A22: 販促
A24: 雑誌掲載

Sheet 2025.10
B1: 週締め | C1: 前週比 | D1: 45925 | E1: 45926 | F1: 45927 | G1: 45928 | H1: 45929 | I1: 45930 | J1: 45931 | K1: 週締め | L1: 前週比 | M1: 45932 | N1: 45933 | O1: 45934 | P1: 45935 | Q1: 45936 | R1: 45937 | S1: 45938 | T1: 週締め | U1: 前週比 | V1: 45939 | W1: 45940 | X1: 45941 | Y1: 45942 | Z1: 45943 | AA1: 45944 | AB1: 45945 | AC1: 週締め | AD1: 前週比 | AE1: 45946 | AF1: 45947 | AG1: 45948 | AH1: 45949 | AI1: 45950 | AJ1: 45951 | AK1: 45952 | AL1: 週締め | AM1: 前週比 | AN1: 45953 | AO1: 45954 | AP1: 45955 | AQ1: 45956 | AR1: 45957 | AS1: 45958 | AT1: 45959 | AU1: 週締め | AV1: 前週比 | AW1: 45960 | AX1: 45961
D2: 木 | E2: 金 | F2: 土 | G2: 日 | H2: 月 | I2: 火 | J2: 水 | M2: 木 | N2: 金 | O2: 土 | P2: 日 | Q2: 月 | R2: 火 | S2: 水 | V2: 木 | W2: 金 | X2: 土 | Y2: 日 | Z2: 月 | AA2: 火 | AB2: 水 | AE2: 木 | AF2: 金 | AG2: 土 | AH2: 日 | AI2: 月 | AJ2: 火 | AK2: 水 | AN2: 木 | AO2: 金 | AP2: 土 | AQ2: 日 | AR2: 月 | AS2: 火 | AT2: 水 | AW2: 木 | AX2: 金
A3: 売り上げ | B3: 298591 | C3: 0.62 | D3: 13826 | E3: 2750 | F3: 5280 | G3: 6600 | H3: 38830 | I3: 68530 | J3: 2200 | K3: 138016 | L3: 0.46 | M3: 14850 | N3: 30250 | O3: 39160 | P3: 12540 | Q3: 0 | R3: 11660 | S3: 5280 | T3: 113740 | U3: 0.82 | V3: 23650 | W3: 4070 | X3: 22660 | Y3: 5280 | Z3: 35640 | AA3: 8250 | AB3: 21890 | AC3: 121440 | AD3: 1.07 | AE3: 0 | AF3: 39930 | AG3: 17600 | AH3: 62480 | AI3: 5610 | AJ3: 12210 | AK3: 5280 | AL3: 143110 | AM3: 1.18 | AN3: 27390 | AO3: 4070 | AP3: 17600 | AQ3: 3080 | AR3: 0 | AS3: 19250
A4: 注文数（人数） | B4: 35 | C4: 0.81 | D4: 2 | E4: 1 | F4: 1 | G4: 1 | H4: 4 | I4: 6 | J4: 1 | K4: 16 | L4: 0.46 | M4: 2 | N4: 1 | O4: 2 | P4: 3 | Q4: 0 | R4: 1 | S4: 1 | T4: 10 | U4: 0.63 | V4: 1 | W4: 1 | X4: 2 | Y4: 1 | Z4: 4 | AA4: 2 | AB4: 3 | AC4: 14 | AD4: 1.4 | AE4: 0 | AF4: 2 | AG4: 4 | AH4: 3 | AI4: 3 | AJ4: 2 | AK4: 1 | AL4: 15 | AM4: 1.07 | AN4: 1 | AO4: 1 | AP4: 1 | AQ4: 1 | AR4: 0 | AS4: 2
A5: 客単価 | B5: =B3/B4 -> 8531.1714 | C5: 0.76 | D5: =D3/D4 -> 6913 | E5: =E3/E4 -> 2750 | F5: =F3/F4 -> 5280 | G5: =G3/G4 -> 6600 | H5: =H3/H4 -> 9707.5 | I5: =I3/I4 -> 11421.667 | J5: =J3/J4 -> 2200 | K5: =K3/K4 -> 8626 | L5: 1.01 | M5: =M3/M4 -> 7425 | N5: =N3/N4 -> 30250 | O5: =O3/O4 -> 19580 | P5: =P3/P4 -> 4180 | Q5: 0 | R5: =R3/R4 -> 11660 | S5: =S3/S4 -> 5280 | T5: =T3/T4 -> 11374 | U5: 1.31 | V5: =V3/V4 -> 23650 | W5: =W3/W4 -> 4070 | X5: =X3/X4 -> 11330 | Y5: =Y3/Y4 -> 5280 | Z5: =Z3/Z4 -> 8910 | AA5: =AA3/AA4 -> 4125 | AB5: =AB3/AB4 -> 7296.6667 | AC5: =AC3/AC4 -> 8674.2857 | AD5: 0.76 | AE5: 0 | AF5: =AF3/AF4 -> 19965 | AG5: =AG3/AG4 -> 4400 | AH5: =AH3/AH4 -> 20826.667 | AI5: =AI3/AI4 -> 1870 | AJ5: =AJ3/AJ4 -> 6105 | AK5: =AK3/AK4 -> 5280 | AL5: =AL3/AL4 -> 9540.6667 | AM5: 1.09 | AN5: =AN3/AN4 -> 27390 | AO5: =AO3/AO4 -> 4070 | AP5: =AP3/AP4 -> 17600 | AQ5: =AQ3/AQ4 -> 3080 | AR5: 0 | AS5: =AS3/AS4 -> 9625
A6: セッション | B6: 3056 | C6: 1.15 | D6: 311 | E6: 371 | F6: 336 | G6: 401 | H6: 383 | I6: 429 | J6: 309 | K6: 2540 | L6: 0.83 | M6: 378 | N6: 326 | O6: 291 | P6: 410 | Q6: 422 | R6: 537 | S6: 412 | T6: 2776 | U6: 1.09 | V6: 409 | W6: 348 | X6: 327 | Y6: 399 | Z6: 432 | AA6: 481 | AB6: 347 | AC6: 2743 | AD6: 0.99 | AE6: 439 | AF6: 377 | AG6: 403 | AH6: 418 | AI6: 353 | AJ6: 300 | AK6: 372 | AL6: 2662 | AM6: 0.97 | AN6: 313 | AO6: 361 | AP6: 378 | AQ6: 455 | AR6: 351 | AS6: 324
A7: CVR | B7: 0.0111 | C7: 0.74 | D7: 0.0064 | E7: 0.0027 | F7: 0.003 | G7: 0.0025 | H7: 0.0104 | I7: 0.014 | J7: 0.0032 | K7: 0.0063 | L7: 0.57 | M7: 0.0053 | N7: 0.0031 | O7: 0.0069 | P7: 0.0073 | Q7: 0 | R7: 0.0019 | S7: 0.0024 | T7: 0.0036 | U7: 0.57 | V7: 0.0024 | W7: 0.0029 | X7: 0.0061 | Y7: 0.0025 | Z7: 0.0093 | AA7: 0.0042 | AB7: 0.0086 | AC7: 0.0051 | AD7: 1.42 | AE7: 0 | AF7: 0.0053 | AG7: 0.0099 | AH7: 0.0072 | AI7: 0.0085 | AJ7: 0.0067 | AK7: 0.0027 | AL7: 0.0056 | AM7: 1.1 | AN7: 0.0032 | AO7: 0.0028 | AP7: 0.0026 | AQ7: 0.0022 | AR7: 0 | AS7: 0.0062
A8: IG FOLLOWER
A9: 販売アイテム
A19: 広告
A20: KOL投稿有無
A21: 販促
A22: 販促
A24: 雑誌掲載
